Workbook

Sheet Ringkasan
A1: Metrik | B1: Nilai
A2: Jumlah artikel | B2: =COUNTA(Artikel!A2:A2182) -> 2181
A3: Artikel dengan ≥1 tempat | B3: =COUNTIF(Artikel!C2:C2182,">0") -> 1049
A4: Jumlah baris tempat | B4: =COUNTA(Tempat!A2:A1789) -> 1788
A5: Tempat viral eksplisit | B5: =COUNTIF(Tempat!Q2:Q1789,"Ya") -> 492
A6: Kategori: Kafe | B6: =COUNTIF(Tempat!D2:D1789,"Kafe") -> 216
A7: Kategori: Restoran | B7: =COUNTIF(Tempat!D2:D1789,"Restoran") -> 583
A8: Kategori: Wisata Alam | B8: =COUNTIF(Tempat!D2:D1789,"Wisata Alam") -> 380
A9: Kategori: Museum | B9: =COUNTIF(Tempat!D2:D1789,"Museum") -> 110
A10: Kategori: Wahana | B10: =COUNTIF(Tempat!D2:D1789,"Wahana") -> 53
A11: Kategori: Pameran | B11: =COUNTIF(Tempat!D2:D1789,"Pameran") -> 204
A12: Kategori: lainnya | B12: =COUNTIF(Tempat!D2:D1789,"lainnya") -> 242
A13: Artikel judul Sesuai | B13: =COUNTIF(Artikel!K2:K2182,"Sesuai") -> 282
A14: Artikel judul Ragu | B14: =COUNTIF(Artikel!K2:K2182,"Ragu") -> 58
A15: Artikel judul Tidak sesuai (isi = judul artikel N-1) | B15: =COUNTIF(Artikel!K2:K2182,"Tidak sesuai (isi = judul artikel N-1)") -> 426
A16: Artikel judul Tidak sesuai | B16: =COUNTIF(Artikel!K2:K2182,"Tidak sesuai") -> 1415
A18: Catatan pergeseran data:
A19: • Isi artikel konsisten cocok dengan final_url (lihat "skor URL vs isi" di sheet Artikel) — jadi final_url adalah sumber yang benar untuk setiap tempat.
A20: • Yang bergeser adalah judul/source/published di id_map: sering bukan milik isi tersebut.
A21: • id ~242–800: isi umumnya milik judul artikel N-1 (bergeser 1). Setelah ~800: judul dan isi teracak (isi cocok dengan judul yang jaraknya jauh, sering ±640–650 id).
A22: • Ekstraksi tempat selalu berdasarkan ISI. Bila "judul sesuai isi?" = Tidak sesuai, abaikan judul/source/published dan rujuk final_url.
A24: Catatan kolom lokasi:
A25: • Kelurahan/kecamatan/kota/provinsi diambil dari lokasi_text; tingkat yang tidak disebut dilengkapi dari pengetahuan geografis hanya bila yakin (lihat kolom "sumber wilayah": teks / teks+inferensi / inferensi). Kosong = tidak disebut & tidak yakin.
A26: • Koordinat TIDAK berasal dari layanan geocoding (akses internet diblokir di lingkungan kerja), melainkan perkiraan. Kolom "presisi koordinat" menjelaskan titik apa yang diwakili: titik tempat (landmark terkenal) atau pusat kelurahan/kecamatan/kota/provinsi.
A27: • Sudah divalidasi otomatis: nama provinsi (38 resmi, termasuk pemekaran Papua), konsistensi kota/kabupaten→provinsi, dan koordinat berada dalam batas provinsinya. Untuk analisis tingkat titik, sebaiknya verifikasi ulang dengan Google Maps/geocoder.
A28: • Nama kota yang ambigu (mis. "Bogor", "Malang", "Bekasi" tanpa keterangan Kota/Kabupaten) dibiarkan kosong di kolom kota/kabupaten; koordinat memakai pusat provinsi.

Sheet Tempat
A1: article_id | B1: batch | C1: nama_tempat | D1: kategori | E1: lokasi_text | F1: kelurahan/desa | G1: kecamatan | H1: kota/kabupaten | I1: provinsi | J1: latitude | K1: longitude | L1: presisi koordinat | M1: sumber wilayah | N1: catatan lokasi | O1: alasan_viral | P1: indikasi_waktu | Q1: is_explicitly_viral | R1: confidence | S1: final_url (sumber isi) | T1: domain URL | U1: judul (id_map) | V1: source (id_map) | W1: published (id_map) | X1: judul sesuai isi?
A2: 1 | B2: 001 | C2: Soto Mie Agih | D2: Restoran | E2: Jalan Suryakencana No.313, Babakan Pasar, Bogor Tengah, Bogor | F2: Babakan Pasar | G2: Bogor Tengah | H2: Kota Bogor | I2: Jawa Barat | J2: -6.605 | K2: 106.8 | L2: Pusat kelurahan/desa | M2: teks+inferensi | O2: Soto mie legendaris Bogor sejak 1965-an, menu babat hingga jumbo | Q2: Tidak | R2: 0.9 | S2: https://food.detik.com/rumah-makan/d-8679688/awas-kalap-ini-7-tempat-makan-soto-mie-legendaris-di-jakarta-dan-bogor | T2: food.detik.com | U2: Awas Kalap! Ini 7 Tempat Makan Soto Mie Legendaris di Jakarta dan Bogor - detikFood | V2: detikFood | W2: 2026-09-26 | X2: Sesuai
A3: 1 | B3: 001 | C3: Soto Mie Sarodja | D3: Restoran | E3: Jalan Danau Tondano No.27, Pejompongan, Jakarta Pusat | F3: Bendungan Hilir | G3: Tanah Abang | H3: Kota Jakarta Pusat | I3: DKI Jakarta | J3: -6.209 | K3: 106.81 | L3: Pusat kelurahan/desa | M3: teks+inferensi | N3: Pejompongan adalah kawasan di Kel. Bendungan Hilir | O3: Soto mie sejak 1970, diteruskan generasi kedua | Q3: Tidak | R3: 0.9 | S3: https://food.detik.com/rumah-makan/d-8679688/awas-kalap-ini-7-tempat-makan-soto-mie-legendaris-di-jakarta-dan-bogor | T3: food.detik.com | U3: Awas Kalap! Ini 7 Tempat Makan Soto Mie Legendaris di Jakarta dan Bogor - detikFood | V3: detikFood | W3: 2026-09-26 | X3: Sesuai
A4: 1 | B4: 001 | C4: Soto Mie Theresia | D4: Restoran | E4: Jalan Gereja Theresia No.43, Menteng, Jakarta Pusat | F4: Gondangdia | G4: Menteng | H4: Kota Jakarta Pusat | I4: DKI Jakarta | J4: -6.188 | K4: 106.827 | L4: Pusat kelurahan/desa | M4: teks+inferensi | O4: Soto mie legendaris sejak 1972 di kawasan Kuliner Theresia | Q4: Tidak | R4: 0.9 | S4: https://food.detik.com/rumah-makan/d-8679688/awas-kalap-ini-7-tempat-makan-soto-mie-legendaris-di-jakarta-dan-bogor | T4: food.detik.com | U4: Awas Kalap! Ini 7 Tempat Makan Soto Mie Legendaris di Jakarta dan Bogor - detikFood | V4: detikFood | W4: 2026-09-26 | X4: Sesuai
A5: 1 | B5: 001 | C5: Soto Mie Pak Fauzy | D5: Restoran | E5: Kawasan Suryakencana, Bogor | G5: Bogor Tengah | H5: Kota Bogor | I5: Jawa Barat | J5: -6.598 | K5: 106.797 | L5: Pusat kecamatan | M5: teks+inferensi | N5: Kawasan Jalan Suryakencana | O5: Soto mie legendaris sejak 1974 | Q5: Tidak | R5: 0.85 | S5: https://food.detik.com/rumah-makan/d-8679688/awas-kalap-ini-7-tempat-makan-soto-mie-legendaris-di-jakarta-dan-bogor | T5: food.detik.com | U5: Awas Kalap! Ini 7 Tempat Makan Soto Mie Legendaris di Jakarta dan Bogor - detikFood | V5: detikFood | W5: 2026-09-26 | X5: Sesuai
A6: 2 | B6: 001 | C6: Gudeg Yu Djum | D6: Restoran | E6: Jl. Wijilan No. 167, Panembahan, Kraton, Yogyakarta | F6: Panembahan | G6: Kraton | H6: Kota Yogyakarta | I6: DI Yogyakarta | J6: -7.806 | K6: 110.367 | L6: Pusat kelurahan/desa | M6: teks+inferensi | O6: Ikon gudeg Jogja sejak 1950-an, harga ekonomis | Q6: Tidak | R6: 0.9 | S6: https://rri.co.id/yogyakarta/kuliner/2752639/rekomendasi-7-tempat-makan-ramah-kantong-di-jogja-dan-tips-menggunakan-grabfood | T6: rri.co.id | U6: Rekomendasi 7 Tempat Makan Ramah Kantong di Jogja dan Tips Menggunakan GrabFood - RRI.co.id | V6: RRI.co.id | W6: 2026-09-23 | X6: Sesuai
A7: 2 | B7: 001 | C7: Gudeg Pawon | D7: Restoran | E7: Yogyakarta | H7: Kota Yogyakarta | I7: DI Yogyakarta | J7: -7.797 | K7: 110.37 | L7: Pusat kota/kabupaten | M7: teks+inferensi | O7: Gudeg dimasak langsung di dapur tradisional, pengalaman unik | Q7: Tidak | R7: 0.8 | S7: https://rri.co.id/yogyakarta/kuliner/2752639/rekomendasi-7-tempat-makan-ramah-kantong-di-jogja-dan-tips-menggunakan-grabfood | T7: rri.co.id | U7: Rekomendasi 7 Tempat Makan Ramah Kantong di Jogja dan Tips Menggunakan GrabFood - RRI.co.id | V7: RRI.co.id | W7: 2026-09-23 | X7: Sesuai
A8: 3 | B8: 001 | C8: RM Abah Harja | D8: Restoran | E8: Jl. Halimun No.8, Malabar, Kec. Lengkong, Kota Bandung | F8: Malabar | G8: Lengkong | H8: Kota Bandung | I8: Jawa Barat | J8: -6.928 | K8: 107.62 | L8: Pusat kelurahan/desa | M8: teks+inferensi | O8: Restoran Sunda baru, punya sawah dan peternakan sendiri, ayam bekakak; masuk daftar tempat makan viral Bandung 2026 | P8: 2026 | Q8: Ya | R8: 0.9 | S8: https://www.nibble.id/tempat-makan-viral-di-bandung-2026/ | T8: www.nibble.id | U8: 10 Tempat Makan Viral di Bandung 2026 - nibble.id | V8: nibble.id | W8: 2026-06-09 | X8: Sesuai
A9: 3 | B9: 001 | C9: RM Wangi Seruni | D9: Restoran | E9: Bandung | H9: Kota Bandung | I9: Jawa Barat | J9: -6.917 | K9: 107.619 | L9: Pusat kota/kabupaten | M9: teks+inferensi | N9: Bandung diasumsikan Kota Bandung | O9: Ayam goreng seruni, konsep makanan rumahan; disebut tempat makan viral Bandung 2026 | P9: 2026 | Q9: Ya | R9: 0.85 | S9: https://www.nibble.id/tempat-makan-viral-di-bandung-2026/ | T9: www.nibble.id | U9: 10 Tempat Makan Viral di Bandung 2026 - nibble.id | V9: nibble.id | W9: 2026-06-09 | X9: Sesuai
A10: 4 | B10: 001 | C10: TikTok Food Fest 2026 | D10: Pameran | E10: Hutan Kota Gelora Bung Karno (GBK), Jakarta | F10: Gelora | G10: Tanah Abang | H10: Kota Jakarta Pusat | I10: DKI Jakarta | J10: -6.2186 | K10: 106.8019 | L10: Titik tempat | M10: teks+inferensi | N10: Kawasan GBK Senayan | O10: Festival kuliner gratis dengan 40+ tenant kuliner viral TikTok | P10: 26–27 September 2026 | Q10: Ya | R10: 0.9 | S10: https://aktualita.co/ragam/tiktok-food-fest-2026-hari-terakhir-gbk | T10: aktualita.co | U10: TikTok Food Fest 2026 Hari Terakhir di GBK, Ada 40 Lebih Tenant hingga Kuliner Viral - Aktualita.co | V10: Aktualita.co | W10: 2026-09-27 | X10: Sesuai
A11: 4 | B11: 001 | C11: Mad Bagel | D11: Kafe | E11: Tenant TikTok Food Fest, GBK, Jakarta | F11: Gelora | G11: Tanah Abang | H11: Kota Jakarta Pusat | I11: DKI Jakarta | J11: -6.2186 | K11: 106.8019 | L11: Titik tempat | M11: teks+inferensi | N11: Kawasan GBK Senayan | O11: Bagel manis dan gurih, kuliner populer di media sosial | Q11: Ya | R11: 0.75 | S11: https://aktualita.co/ragam/tiktok-food-fest-2026-hari-terakhir-gbk | T11: aktualita.co | U11: TikTok Food Fest 2026 Hari Terakhir di GBK, Ada 40 Lebih Tenant hingga Kuliner Viral - Aktualita.co | V11: Aktualita.co | W11: 2026-09-27 | X11: Sesuai
A12: 4 | B12: 001 | C12: RM Lokiin | D12: Restoran | E12: Tenant TikTok Food Fest, GBK, Jakarta | F12: Gelora | G12: Tanah Abang | H12: Kota Jakarta Pusat | I12: DKI Jakarta | J12: -6.2186 | K12: 106.8019 | L12: Titik tempat | M12: teks+inferensi | N12: Kawasan GBK Senayan | O12: Nasi dengan beragam lauk termasuk nasi lidah, populer di medsos | Q12: Ya | R12: 0.75 | S12: https://aktualita.co/ragam/tiktok-food-fest-2026-hari-terakhir-gbk | T12: aktualita.co | U12: TikTok Food Fest 2026 Hari Terakhir di GBK, Ada 40 Lebih Tenant hingga Kuliner Viral - Aktualita.co | V12: Aktualita.co | W12: 2026-09-27 | X12: Sesuai
A13: 4 | B13: 001 | C13: Chuchat | D13: Kafe | E13: Tenant TikTok Food Fest, GBK, Jakarta | F13: Gelora | G13: Tanah Abang | H13: Kota Jakarta Pusat | I13: DKI Jakarta | J13: -6.2186 | K13: 106.8019 | L13: Titik tempat | M13: teks+inferensi | N13: Kawasan GBK Senayan | O13: Tenant minuman populer di media sosial | Q13: Ya | R13: 0.7 | S13: https://aktualita.co/ragam/tiktok-food-fest-2026-hari-terakhir-gbk | T13: aktualita.co | U13: TikTok Food Fest 2026 Hari Terakhir di GBK, Ada 40 Lebih Tenant hingga Kuliner Viral - Aktualita.co | V13: Aktualita.co | W13: 2026-09-27 | X13: Sesuai
A14: 4 | B14: 001 | C14: Fuku | D14: Kafe | E14: Tenant TikTok Food Fest, GBK, Jakarta | F14: Gelora | G14: Tanah Abang | H14: Kota Jakarta Pusat | I14: DKI Jakarta | J14: -6.2186 | K14: 106.8019 | L14: Titik tempat | M14: teks+inferensi | N14: Kawasan GBK Senayan | O14: Gelato mochi, populer di media sosial | Q14: Ya | R14: 0.7 | S14: https://aktualita.co/ragam/tiktok-food-fest-2026-hari-terakhir-gbk | T14: aktualita.co | U14: TikTok Food Fest 2026 Hari Terakhir di GBK, Ada 40 Lebih Tenant hingga Kuliner Viral - Aktualita.co | V14: Aktualita.co | W14: 2026-09-27 | X14: Sesuai
A15: 4 | B15: 001 | C15: Eight Tarts | D15: Kafe | E15: Tenant TikTok Food Fest, GBK, Jakarta | F15: Gelora | G15: Tanah Abang | H15: Kota Jakarta Pusat | I15: DKI Jakarta | J15: -6.2186 | K15: 106.8019 | L15: Titik tempat | M15: teks+inferensi | N15: Kawasan GBK Senayan | O15: Berbagai varian egg tart | Q15: Ya | R15: 0.7 | S15: https://aktualita.co/ragam/tiktok-food-fest-2026-hari-terakhir-gbk | T15: aktualita.co | U15: TikTok Food Fest 2026 Hari Terakhir di GBK, Ada 40 Lebih Tenant hingga Kuliner Viral - Aktualita.co | V15: Aktualita.co | W15: 2026-09-27 | X15: Sesuai
A16: 4 | B16: 001 | C16: Ayam Renald | D16: Restoran | E16: Tenant TikTok Food Fest, GBK, Jakarta | F16: Gelora | G16: Tanah Abang | H16: Kota Jakarta Pusat | I16: DKI Jakarta | J16: -6.2186 | K16: 106.8019 | L16: Titik tempat | M16: teks+inferensi | N16: Kawasan GBK Senayan | O16: Olahan ayam populer di media sosial | Q16: Ya | R16: 0.7 | S16: https://aktualita.co/ragam/tiktok-food-fest-2026-hari-terakhir-gbk | T16: aktualita.co | U16: TikTok Food Fest 2026 Hari Terakhir di GBK, Ada 40 Lebih Tenant hingga Kuliner Viral - Aktualita.co | V16: Aktualita.co | W16: 2026-09-27 | X16: Sesuai
A17: 4 | B17: 001 | C17: Aldi's Burger | D17: Restoran | E17: Tenant TikTok Food Fest, GBK, Jakarta | F17: Gelora | G17: Tanah Abang | H17: Kota Jakarta Pusat | I17: DKI Jakarta | J17: -6.2186 | K17: 106.8019 | L17: Titik tempat | M17: teks+inferensi | N17: Kawasan GBK Senayan | O17: Burger populer di media sosial | Q17: Ya | R17: 0.7 | S17: https://aktualita.co/ragam/tiktok-food-fest-2026-hari-terakhir-gbk | T17: aktualita.co | U17: TikTok Food Fest 2026 Hari Terakhir di GBK, Ada 40 Lebih Tenant hingga Kuliner Viral - Aktualita.co | V17: Aktualita.co | W17: 2026-09-27 | X17: Sesuai
A18: 5 | B18: 001 | C18: Sop Janda | D18: Restoran | E18: Jl. Raya Pekayon No. 11, Pekayon Jaya, Kec. Bekasi Selatan, Bekasi | F18: Pekayon Jaya | G18: Bekasi Selatan | H18: Kota Bekasi | I18: Jawa Barat | J18: -6.26 | K18: 106.988 | L18: Pusat kelurahan/desa | M18: teks+inferensi | O18: Perpaduan masakan Jawa-Sunda, sop janda daging dan sate maranggi, selalu ramai | Q18: Tidak | R18: 0.8 | S18: https://www.tripzilla.id/tempat-makan-di-bekasi-hits-legendaris-dan-ramah-kantong/27718 | T18: www.tripzilla.id | U18: Buat YTTA, Tempat Makan Di Bekasi Bikin Orang Jakarta Rela Antre! - tripzilla.id | V18: tripzilla.id | W18: 2026-09-22 | X18: Ragu
A19: 5 | B19: 001 | C19: Bebek Kaleyo | D19: Restoran | E19: Jl. Raya Kalimalang Kompleks Ruko Duta Permai, Bekasi | H19: Kota Bekasi | I19: Jawa Barat | J19: -6.238 | K19: 106.976 | L19: Pusat kota/kabupaten | M19: teks+inferensi | N19: Kawasan Kalimalang | O19: Bebek goreng renyah favorit keluarga | Q19: Tidak | R19: 0.85 | S19: https://www.tripzilla.id/tempat-makan-di-bekasi-hits-legendaris-dan-ramah-kantong/27718 | T19: www.tripzilla.id | U19: Buat YTTA, Tempat Makan Di Bekasi Bikin Orang Jakarta Rela Antre! - tripzilla.id | V19: tripzilla.id | W19: 2026-09-22 | X19: Ragu
A20: 5 | B20: 001 | C20: Fish n' Chops | D20: Restoran | E20: Jl. Boulevard Raya Ruko RGB No. 57-58, Jaka Setia, Bekasi | F20: Jaka Setia | G20: Bekasi Selatan | H20: Kota Bekasi | I20: Jawa Barat | J20: -6.268 | K20: 106.97 | L20: Pusat kelurahan/desa | M20: teks+inferensi | O20: Seafood platter krispi dengan harga bersahabat | Q20: Tidak | R20: 0.8 | S20: https://www.tripzilla.id/tempat-makan-di-bekasi-hits-legendaris-dan-ramah-kantong/27718 | T20: www.tripzilla.id | U20: Buat YTTA, Tempat Makan Di Bekasi Bikin Orang Jakarta Rela Antre! - tripzilla.id | V20: tripzilla.id | W20: 2026-09-22 | X20: Ragu
A21: 6 | B21: 001 | C21: Ayam Goreng Kalibogor | D21: Restoran | E21: Purwokerto, Banyumas | H21: Kabupaten Banyumas | I21: Jawa Tengah | J21: -7.45 | K21: 109.17 | L21: Pusat kota/kabupaten | M21: teks+inferensi | N21: Purwokerto (ibu kota Kab. Banyumas) | O21: Warung ayam goreng legendaris dengan resep rempah, ramai antrean | Q21: Tidak | R21: 0.75 | S21: https://jogja.disway.id/gaya-hidup/read/702022/deretan-warung-ayam-goreng-legendaris-paling-hits-di-purwokerto-dengan-cita-rasa-rempah | T21: jogja.disway.id | U21: Deretan Warung Ayam Goreng Legendaris Paling Hits di Purwokerto dengan Cita Rasa Rempah - jogja.disway.id - Disway Jogja | V21: Disway Jogja | W21: 2026-09-27 | X21: Sesuai
A22: 7 | B22: 001 | C22: Warung Amanda | D22: Restoran | E22: Jl. Raya Taman Pinang Indah No.6, Banjarbendo, Kec. Sidoarjo | F22: Banjarbendo | G22: Sidoarjo | H22: Kabupaten Sidoarjo | I22: Jawa Timur | J22: -7.439 | K22: 112.696 | L22: Pusat kelurahan/desa | M22: teks+inferensi | O22: Sego sambel lento khas Sidoarjo, buka 24 jam, harga murah | Q22: Tidak | R22: 0.85 | S22: https://jatim.idntimes.com/food/dining-guide/10-rekomendasi-kuliner-malam-di-sidoarjo-cocok-bagi-pencinta-kuliner-c1c2-01-njfwj-gnsrbz | T22: jatim.idntimes.com | U22: 10 Rekomendasi Kuliner Malam Sidoarjo, Gak Takut Lapar Saat Begadang - IDN Times Jatim | V22: IDN Times Jatim | W22: 2026-09-16 | X22: Sesuai
A23: 7 | B23: 001 | C23: Warung sego babat Jalan Diponegoro | D23: Restoran | E23: Jalan Diponegoro, Sidoarjo | G23: Sidoarjo | H23: Kabupaten Sidoarjo | I23: Jawa Timur | J23: -7.45 | K23: 112.715 | L23: Pusat kecamatan | M23: teks+inferensi | O23: Sego babat terkenal, selalu antre setiap malam, nasi empal | Q23: Tidak | R23: 0.6 | S23: https://jatim.idntimes.com/food/dining-guide/10-rekomendasi-kuliner-malam-di-sidoarjo-cocok-bagi-pencinta-kuliner-c1c2-01-njfwj-gnsrbz | T23: jatim.idntimes.com | U23: 10 Rekomendasi Kuliner Malam Sidoarjo, Gak Takut Lapar Saat Begadang - IDN Times Jatim | V23: IDN Times Jatim | W23: 2026-09-16 | X23: Sesuai
A24: 8 | B24: 001 | C24: Riung Tenda | D24: Restoran | E24: Jl. Balai Pustaka Timur No.2, Rawamangun, Pulo Gadung, Jakarta Timur | F24: Rawamangun | G24: Pulo Gadung | H24: Kota Jakarta Timur | I24: DKI Jakarta | J24: -6.196 | K24: 106.887 | L24: Pusat kelurahan/desa | M24: teks+inferensi | O24: Masakan Sunda murah, sambal dadak | Q24: Tidak | R24: 0.8 | S24: https://www.rumah123.com/explore/kota-jakarta-timur/tempat-makan-di-jakarta-timur-yang-murah-dan-enak/ | T24: www.rumah123.com | U24: 7 Rekomendasi Tempat Makan di Jakarta Timur yang Murah dan Enak - rumah123.com | V24: rumah123.com | W24: 2026-04-18 | X24: Sesuai
A25: 8 | B25: 001 | C25: Sari Idaman | D25: Restoran | E25: Jl. Cipinang Jaya Raya No.25A, Cipinang Muara, Jakarta Timur | F25: Cipinang Muara | G25: Jatinegara | H25: Kota Jakarta Timur | I25: DKI Jakarta | J25: -6.229 | K25: 106.892 | L25: Pusat kelurahan/desa | M25: teks+inferensi | O25: Menu Sunda, olahan gurame dan ayam goreng | Q25: Tidak | R25: 0.8 | S25: https://www.rumah123.com/explore/kota-jakarta-timur/tempat-makan-di-jakarta-timur-yang-murah-dan-enak/ | T25: www.rumah123.com | U25: 7 Rekomendasi Tempat Makan di Jakarta Timur yang Murah dan Enak - rumah123.com | V25: rumah123.com | W25: 2026-04-18 | X25: Sesuai
A26: 8 | B26: 001 | C26: Lesehan Gurame Pemuda | D26: Restoran | E26: Jl. Pemuda No.77, Rawamangun, Jakarta Timur | F26: Rawamangun | G26: Pulo Gadung | H26: Kota Jakarta Timur | I26: DKI Jakarta | J26: -6.196 | K26: 106.887 | L26: Pusat kelurahan/desa | M26: teks+inferensi | O26: Olahan gurame dan seafood konsep lesehan | Q26: Tidak | R26: 0.8 | S26: https://www.rumah123.com/explore/kota-jakarta-timur/tempat-makan-di-jakarta-timur-yang-murah-dan-enak/ | T26: www.rumah123.com | U26: 7 Rekomendasi Tempat Makan di Jakarta Timur yang Murah dan Enak - rumah123.com | V26: rumah123.com | W26: 2026-04-18 | X26: Sesuai
A27: 8 | B27: 001 | C27: Sambal Bakar Indonesia | D27: Restoran | E27: Jl. Lingkar Duren Sawit No.3, Duren Sawit, Jakarta Timur | G27: Duren Sawit | H27: Kota Jakarta Timur | I27: DKI Jakarta | J27: -6.23 | K27: 106.915 | L27: Pusat kecamatan | M27: teks+inferensi | O27: Sedang populer dengan konsep sambal bakar unik | Q27: Tidak | R27: 0.8 | S27: https://www.rumah123.com/explore/kota-jakarta-timur/tempat-makan-di-jakarta-timur-yang-murah-dan-enak/ | T27: www.rumah123.com | U27: 7 Rekomendasi Tempat Makan di Jakarta Timur yang Murah dan Enak - rumah123.com | V27: rumah123.com | W27: 2026-04-18 | X27: Sesuai
A28: 8 | B28: 001 | C28: Teras Rumah Nenek | D28: Kafe | E28: Jl. Abdulrahman No.46, Cibubur, Ciracas, Jakarta Timur | F28: Cibubur | G28: Ciracas | H28: Kota Jakarta Timur | I28: DKI Jakarta | J28: -6.364 | K28: 106.883 | L28: Pusat kelurahan/desa | M28: teks+inferensi | O28: Tempat makan sekaligus kafe asri dengan area outdoor luas | Q28: Tidak | R28: 0.8 | S28: https://www.rumah123.com/explore/kota-jakarta-timur/tempat-makan-di-jakarta-timur-yang-murah-dan-enak/ | T28: www.rumah123.com | U28: 7 Rekomendasi Tempat Makan di Jakarta Timur yang Murah dan Enak - rumah123.com | V28: rumah123.com | W28: 2026-04-18 | X28: Sesuai
A29: 9 | B29: 001 | C29: Bakso President | D29: Restoran | E29: Malang | H29: Kota Malang | I29: Jawa Timur | J29: -7.98 | K29: 112.63 | L29: Pusat kota/kabupaten | M29: teks+inferensi | N29: Malang diasumsikan Kota Malang | O29: Bakso legendaris sejak 1977 di sisi rel kereta api aktif | Q29: Tidak | R29: 0.9 | S29: https://erafone.com/artikel/post/wisata-kuliner-malang-04 | T29: erafone.com | U29: 10 Rekomendasi Destinasi Wisata Kuliner Malang yang Enak - Erafone | V29: Erafone | W29: 2026-08-18 | X29: Sesuai
A30: 9 | B30: 001 | C30: Rawon Nguling | D30: Restoran | E30: Malang | H30: Kota Malang | I30: Jawa Timur | J30: -7.98 | K30: 112.63 | L30: Pusat kota/kabupaten | M30: teks+inferensi | N30: Malang diasumsikan Kota Malang | O30: Rawon khas Jawa Timur sejak 1980-an, kuah kluwek | Q30: Tidak | R30: 0.85 | S30: https://erafone.com/artikel/post/wisata-kuliner-malang-04 | T30: erafone.com | U30: 10 Rekomendasi Destinasi Wisata Kuliner Malang yang Enak - Erafone | V30: Erafone | W30: 2026-08-18 | X30: Sesuai
A31: 9 | B31: 001 | C31: Depot Hok Lay | D31: Restoran | E31: Malang | H31: Kota Malang | I31: Jawa Timur | J31: -7.98 | K31: 112.63 | L31: Pusat kota/kabupaten | M31: teks+inferensi | N31: Malang diasumsikan Kota Malang | O31: Destinasi kuliner legendaris Malang | Q31: Tidak | R31: 0.8 | S31: https://erafone.com/artikel/post/wisata-kuliner-malang-04 | T31: erafone.com | U31: 10 Rekomendasi Destinasi Wisata Kuliner Malang yang Enak - Erafone | V31: Erafone | W31: 2026-08-18 | X31: Sesuai
A32: 10 | B32: 001 | C32: Laksa Pak Masitar | D32: Restoran | E32: Tangerang | I32: Banten | J32: -6.405 | K32: 106.064 | L32: Pusat provinsi | M32: teks+inferensi | N32: Tangerang ambigu (Kota/Kabupaten Tangerang) | O32: Laksa khas Tangerang legendaris, berjualan 36 tahun | Q32: Tidak | R32: 0.8 | S32: https://www.hipwee.com/travel/tempat-makan-murah-di-tangerang/ | T32: www.hipwee.com | U32: 8 Tempat Makan Murah di Tangerang yang Enak dan Bikin Kenyang - Hipwee | V32: Hipwee | W32: 2026-07-22 | X32: Sesuai
A33: 10 | B33: 001 | C33: Warung Bogana May-May | D33: Restoran | E33: Pasar Modern BSD, Tangerang Selatan | F33: Lengkong Gudang | G33: Serpong | H33: Kota Tangerang Selatan | I33: Banten | J33: -6.302 | K33: 106.68 | L33: Pusat kelurahan/desa | M33: teks+inferensi | N33: Pasar Modern BSD | O33: Nasi bogana dengan isian lengkap, murah | Q33: Tidak | R33: 0.8 | S33: https://www.hipwee.com/travel/tempat-makan-murah-di-tangerang/ | T33: www.hipwee.com | U33: 8 Tempat Makan Murah di Tangerang yang Enak dan Bikin Kenyang - Hipwee | V33: Hipwee | W33: 2026-07-22 | X33: Sesuai
A34: 11 | B34: 001 | C34: Harmadha Joglo | D34: Restoran | E34: Jl. Diponegoro No. 21, Nganten, Selosari, Kecamatan Magetan, Kabupaten Magetan | F34: Selosari | G34: Magetan | H34: Kabupaten Magetan | I34: Jawa Timur | J34: -7.65 | K34: 111.33 | L34: Pusat kelurahan/desa | M34: teks+inferensi | O34: Restoran dan kafe hits, sop iga dan rawon | Q34: Tidak | R34: 0.9 | S34: https://rri.co.id/madiun/kuliner/2758486/harmadha-joglo-tempat-kuliner-hits-magetan | T34: rri.co.id | U34: Harmadha Joglo, Tempat Kuliner Hits Magetan - RRI.co.id | V34: RRI.co.id | W34: 2026-09-25 | X34: Sesuai
A35: 12 | B35: 001 | C35: RM Mang Iki | D35: Restoran | E35: Jl. Pasar Baru No. 84, Ciwalen, Garut Kota, Garut | F35: Ciwalen | G35: Garut Kota | H35: Kabupaten Garut | I35: Jawa Barat | J35: -7.213 | K35: 107.905 | L35: Pusat kelurahan/desa | M35: teks+inferensi | O35: Rumah makan Sunda legendaris sejak 1970 | Q35: Tidak | R35: 0.9 | S35: https://food.detik.com/tempat-makan/d-8549503/7-tempat-makan-di-garut-yang-enak-dan-murah-favorit-warga-lokal | T35: food.detik.com | U35: 7 Tempat Makan di Garut yang Enak dan Murah, Favorit Warga Lokal - detikFood | V35: detikFood | W35: 2026-06-27 | X35: Sesuai
A36: 12 | B36: 001 | C36: RM Saung Cikenceh | D36: Restoran | E36: Garut Kota, Garut | G36: Garut Kota | H36: Kabupaten Garut | I36: Jawa Barat | J36: -7.215 | K36: 107.9 | L36: Pusat kecamatan | M36: teks+inferensi | O36: Hidangan Sunda autentik, suasana santai, harga terjangkau | Q36: Tidak | R36: 0.85 | S36: https://food.detik.com/tempat-makan/d-8549503/7-tempat-makan-di-garut-yang-enak-dan-murah-favorit-warga-lokal | T36: food.detik.com | U36: 7 Tempat Makan di Garut yang Enak dan Murah, Favorit Warga Lokal - detikFood | V36: detikFood | W36: 2026-06-27 | X36: Sesuai
A37: 13 | B37: 001 | C37: Ayam Bakar Christina (ABC) | D37: Restoran | E37: Jl. Margonda Raya No. 420, Pondok Cina, Beji, Depok | F37: Pondok Cina | G37: Beji | H37: Kota Depok | I37: Jawa Barat | J37: -6.37 | K37: 106.83 | L37: Pusat kelurahan/desa | M37: teks+inferensi | O37: Ayam bakar legendaris sejak 1986 | Q37: Tidak | R37: 0.9 | S37: https://www.tripzilla.id/tempat-makan-di-depok/27073 | T37: www.tripzilla.id | U37: 🍽️ [Paling Update] 30+ Tempat Makan di Depok Untuk Pecinta Kuliner! - tripzilla.id | V37: tripzilla.id | W37: 2026-05-21 | X37: Sesuai
A38: 13 | B38: 001 | C38: Rumah Makan Gandy | D38: Restoran | E38: Jl. Raya Muchtar No. 24, Bojongsari, Sawangan, Depok | G38: Sawangan | H38: Kota Depok | I38: Jawa Barat | J38: -6.4 | K38: 106.765 | L38: Pusat kecamatan | M38: teks+inferensi | N38: Bojongsari kini kecamatan tersendiri (pemekaran dari Sawangan); kelurahan ambigu | O38: Masakan Betawi-Sunda sejak era 70-an, pecak gurame | Q38: Tidak | R38: 0.85 | S38: https://www.tripzilla.id/tempat-makan-di-depok/27073 | T38: www.tripzilla.id | U38: 🍽️ [Paling Update] 30+ Tempat Makan di Depok Untuk Pecinta Kuliner! - tripzilla.id | V38: tripzilla.id | W38: 2026-05-21 | X38: Sesuai
A39: 13 | B39: 001 | C39: Nasi Uduk H. Yoyo | D39: Restoran | E39: Depok | H39: Kota Depok | I39: Jawa Barat | J39: -6.402 | K39: 106.795 | L39: Pusat kota/kabupaten | M39: teks+inferensi | O39: Salah satu destinasi kuliner tertua di Depok, 60+ tahun | Q39: Tidak | R39: 0.8 | S39: https://www.tripzilla.id/tempat-makan-di-depok/27073 | T39: www.tripzilla.id | U39: 🍽️ [Paling Update] 30+ Tempat Makan di Depok Untuk Pecinta Kuliner! - tripzilla.id | V39: tripzilla.id | W39: 2026-05-21 | X39: Sesuai
A40: 14 | B40: 001 | C40: RM Salam Sereh | D40: Restoran | E40: Jl. Raya Kp. Sawah, Bojong, Kec. Kemang, Kab. Bogor | F40: Bojong | G40: Kemang | H40: Kabupaten Bogor | I40: Jawa Barat | J40: -6.504 | K40: 106.745 | L40: Pusat kecamatan | M40: teks+inferensi | O40: Restoran baru Sunda di tengah persawahan | P40: Juni 2026 | Q40: Tidak | R40: 0.85 | S40: https://www.nibble.id/restoran-baru-di-bogor-juni-2026/ | T40: www.nibble.id | U40: 10 Restoran Baru di Bogor Juni 2026 - nibble.id | V40: nibble.id | W40: 2026-06-07 | X40: Sesuai
A41: 14 | B41: 001 | C41: The Layer Cafe | D41: Kafe | E41: Jl. Terobosan No.01, Cipayung Datar, Kec. Megamendung, Kab. Bogor | F41: Cipayung Datar | G41: Megamendung | H41: Kabupaten Bogor | I41: Jawa Barat | J41: -6.66 | K41: 106.9 | L41: Pusat kecamatan | M41: teks+inferensi | O41: Tempat hangout baru dengan view pegunungan | P41: Juni 2026 | Q41: Tidak | R41: 0.85 | S41: https://www.nibble.id/restoran-baru-di-bogor-juni-2026/ | T41: www.nibble.id | U41: 10 Restoran Baru di Bogor Juni 2026 - nibble.id | V41: nibble.id | W41: 2026-06-07 | X41: Sesuai
A42: 14 | B42: 001 | C42: Padre | D42: Restoran | E42: Kanma Collective, Bogor Selatan | G42: Bogor Selatan | H42: Kota Bogor | I42: Jawa Barat | J42: -6.63 | K42: 106.81 | L42: Pusat kecamatan | M42: teks+inferensi | O42: Restoran Italia Kanma Group buka cabang baru | P42: Juni 2026 | Q42: Tidak | R42: 0.8 | S42: https://www.nibble.id/restoran-baru-di-bogor-juni-2026/ | T42: www.nibble.id | U42: 10 Restoran Baru di Bogor Juni 2026 - nibble.id | V42: nibble.id | W42: 2026-06-07 | X42: Sesuai
A43: 14 | B43: 001 | C43: Two Stories | D43: Kafe | E43: Kanma Collective, Bogor Selatan | G43: Bogor Selatan | H43: Kota Bogor | I43: Jawa Barat | J43: -6.63 | K43: 106.81 | L43: Pusat kecamatan | M43: teks+inferensi | O43: Satu lokasi dengan Padre | Q43: Tidak | R43: 0.5 | S43: https://www.nibble.id/restoran-baru-di-bogor-juni-2026/ | T43: www.nibble.id | U43: 10 Restoran Baru di Bogor Juni 2026 - nibble.id | V43: nibble.id | W43: 2026-06-07 | X43: Sesuai
A44: 14 | B44: 001 | C44: Kopi Nako | D44: Kafe | E44: Kanma Collective, Bogor Selatan | G44: Bogor Selatan | H44: Kota Bogor | I44: Jawa Barat | J44: -6.63 | K44: 106.81 | L44: Pusat kecamatan | M44: teks+inferensi | O44: Satu lokasi dengan Padre | Q44: Tidak | R44: 0.5 | S44: https://www.nibble.id/restoran-baru-di-bogor-juni-2026/ | T44: www.nibble.id | U44: 10 Restoran Baru di Bogor Juni 2026 - nibble.id | V44: nibble.id | W44: 2026-06-07 | X44: Sesuai
A45: 15 | B45: 001 | C45: Sate Madura Cak Mat | D45: Restoran | E45: Sekitar Kelapa Gading, Jakarta Utara | G45: Kelapa Gading | H45: Kota Jakarta Utara | I45: DKI Jakarta | J45: -6.16 | K45: 106.905 | L45: Pusat kecamatan | M45: teks+inferensi | O45: Tempat makan populer dekat stasiun LRT Kelapa Gading | Q45: Tidak | R45: 0.6 | S45: https://jogja.disway.id/gaya-hidup/read/701716/wisata-kuliner-tempat-makan-paling-populer-dan-menggugah-selera-di-sekitar-kelapa-gading | T45: jogja.disway.id | U45: Wisata Kuliner Tempat Makan Paling Populer dan Menggugah Selera di Sekitar Kelapa Gading - jogja.disway.id - Disway Jogja | V45: Disway Jogja | W45: 2026-09-13 | X45: Sesuai
A46: 15 | B46: 001 | C46: Ayam Bakar Madu | D46: Restoran | E46: Sekitar Kelapa Gading, Jakarta Utara | G46: Kelapa Gading | H46: Kota Jakarta Utara | I46: DKI Jakarta | J46: -6.16 | K46: 106.905 | L46: Pusat kecamatan | M46: teks+inferensi | O46: Tempat makan populer dekat stasiun LRT Kelapa Gading | Q46: Tidak | R46: 0.55 | S46: https://jogja.disway.id/gaya-hidup/read/701716/wisata-kuliner-tempat-makan-paling-populer-dan-menggugah-selera-di-sekitar-kelapa-gading | T46: jogja.disway.id | U46: Wisata Kuliner Tempat Makan Paling Populer dan Menggugah Selera di Sekitar Kelapa Gading - jogja.disway.id - Disway Jogja | V46: Disway Jogja | W46: 2026-09-13 | X46: Sesuai
A47: 16 | B47: 001 | C47: Kampung Kecil KM 5 | D47: Restoran | E47: KM 5, Palembang | H47: Kota Palembang | I47: Sumatera Selatan | J47: -2.976 | K47: 104.775 | L47: Pusat kota/kabupaten | M47: teks+inferensi | N47: Kawasan KM 5 | O47: Lesehan saung kayu, kolam ikan, playground, ramah anak | Q47: Tidak | R47: 0.85 | S47: https://www.hipwee.com/travel/tempat-makan-keluarga-di-palembang/ | T47: www.hipwee.com | U47: 9 Tempat Makan Keluarga di Palembang yang Nyaman, Enak, dan Ramah Anak - Hipwee | V47: Hipwee | W47: 2026-07-06 | X47: Sesuai
A48: 16 | B48: 001 | C48: Le Garden | D48: Restoran | E48: Palembang Indah Mall, Palembang | G48: Ilir Timur I | H48: Kota Palembang | I48: Sumatera Selatan | J48: -2.979 | K48: 104.755 | L48: Titik tempat | M48: teks+inferensi | O48: Food court indoor garden dengan puluhan tenant | Q48: Tidak | R48: 0.8 | S48: https://www.hipwee.com/travel/tempat-makan-keluarga-di-palembang/ | T48: www.hipwee.com | U48: 9 Tempat Makan Keluarga di Palembang yang Nyaman, Enak, dan Ramah Anak - Hipwee | V48: Hipwee | W48: 2026-07-06 | X48: Sesuai
A49: 17 | B49: 001 | C49: BMB Canteen | D49: Restoran | E49: Jl. Sirnagalih No.1, Cipedes, Kec. Sukajadi, Kota Bandung, Jawa Barat | F49: Cipedes | G49: Sukajadi | H49: Kota Bandung | I49: Jawa Barat | J49: -6.883 | K49: 107.59 | L49: Pusat kelurahan/desa | M49: teks | O49: Tempat makan hits dan viral, antre panjang sebelum buka, corned beef sourdough | P49: 2026 | Q49: Ya | R49: 0.9 | S49: https://www.tripzilla.id/tempat-makan-hits-bandung/27057 | T49: www.tripzilla.id | U49: 13 Tempat Makan Hits dan Viral di Bandung Yang Wajib Kamu Kunjungi - tripzilla.id | V49: tripzilla.id | W49: 2026-05-15 | X49: Sesuai
A50: 17 | B50: 001 | C50: Toko Bubur Dibawah Pohon Rindang | D50: Restoran | E50: Jl. Taman Cibeunying Utara No.24, Cihapit, Kec. Bandung Wetan, Kota Bandung | F50: Cihapit | G50: Bandung Wetan | H50: Kota Bandung | I50: Jawa Barat | J50: -6.903 | K50: 107.625 | L50: Pusat kelurahan/desa | M50: teks+inferensi | O50: Sangat populer, antrean mengular, bubur kanton capit kepiting | Q50: Ya | R50: 0.85 | S50: https://www.tripzilla.id/tempat-makan-hits-bandung/27057 | T50: www.tripzilla.id | U50: 13 Tempat Makan Hits dan Viral di Bandung Yang Wajib Kamu Kunjungi - tripzilla.id | V50: tripzilla.id | W50: 2026-05-15 | X50: Sesuai
A51: 17 | B51: 001 | C51: Pasar Cihapit | D51: lainnya | E51: Kawasan Cihapit, Bandung | F51: Cihapit | G51: Bandung Wetan | H51: Kota Bandung | I51: Jawa Barat | J51: -6.903 | K51: 107.625 | L51: Pusat kelurahan/desa | M51: teks+inferensi | O51: Pasar tradisional yang lagi hits jadi surga kuliner | Q51: Ya | R51: 0.8 | S51: https://www.tripzilla.id/tempat-makan-hits-bandung/27057 | T51: www.tripzilla.id | U51: 13 Tempat Makan Hits dan Viral di Bandung Yang Wajib Kamu Kunjungi - tripzilla.id | V51: tripzilla.id | W51: 2026-05-15 | X51: Sesuai
A52: 18 | B52: 001 | C52: Malindo | D52: Restoran | E52: Kebumen | H52: Kabupaten Kebumen | I52: Jawa Tengah | J52: -7.633 | K52: 109.6 | L52: Pusat kota/kabupaten | M52: teks+inferensi | O52: Menu Nusantara beragam, sambal jadi highlight | Q52: Tidak | R52: 0.75 | S52: https://www.hipwee.com/travel/rekomendasi-tempat-makan-di-kebumen/ | T52: www.hipwee.com | U52: 10 Rekomendasi Tempat Makan di Kebumen yang Enak dan Wajib Kamu Coba - Hipwee | V52: Hipwee | W52: 2026-04-10 | X52: Sesuai
A53: 18 | B53: 001 | C53: Momong Resto | D53: Restoran | E53: Kebumen | H53: Kabupaten Kebumen | I53: Jawa Tengah | J53: -7.633 | K53: 109.6 | L53: Pusat kota/kabupaten | M53: teks+inferensi | O53: Tempat luas untuk makan keluarga besar | Q53: Tidak | R53: 0.8 | S53: https://www.hipwee.com/travel/rekomendasi-tempat-makan-di-kebumen/ | T53: www.hipwee.com | U53: 10 Rekomendasi Tempat Makan di Kebumen yang Enak dan Wajib Kamu Coba - Hipwee | V53: Hipwee | W53: 2026-04-10 | X53: Sesuai
A54: 19 | B54: 001 | C54: Barayam | D54: Restoran | E54: Jalan Hos Cokroaminoto, Ciledug, Tangerang | G54: Ciledug | H54: Kota Tangerang | I54: Banten | J54: -6.23 | K54: 106.708 | L54: Pusat kecamatan | M54: teks+inferensi | O54: Ayam goreng bawang putih crispy, kuliner hits yang belakangan viral | Q54: Ya | R54: 0.85 | S54: https://food.detik.com/rumah-makan/d-8550840/7-kuliner-hits-di-ciledug-yang-lagi-viral-ada-nasi-goreng-yang-antre-1-jam | T54: food.detik.com | U54: 7 Kuliner Hits di Ciledug yang Lagi Viral, Ada Nasi Goreng yang Antre 1 Jam! - detikFood | V54: detikFood | W54: 2026-06-28 | X54: Sesuai
A55: 19 | B55: 001 | C55: Liwet Bakar Derajat | D55: Restoran | E55: Jalan HOS Cokroaminoto, Karang Tengah, Ciledug, Tangerang | F55: Karang Tengah | G55: Karang Tengah | H55: Kota Tangerang | I55: Banten | J55: -6.22 | K55: 106.72 | L55: Pusat kecamatan | M55: teks+inferensi | N55: Karang Tengah adalah kecamatan tersendiri (bukan bagian Ciledug) | O55: Nasi liwet bakar hits di Karang Tengah | Q55: Ya | R55: 0.8 | S55: https://food.detik.com/rumah-makan/d-8550840/7-kuliner-hits-di-ciledug-yang-lagi-viral-ada-nasi-goreng-yang-antre-1-jam | T55: food.detik.com | U55: 7 Kuliner Hits di Ciledug yang Lagi Viral, Ada Nasi Goreng yang Antre 1 Jam! - detikFood | V55: detikFood | W55: 2026-06-28 | X55: Sesuai
A56: 19 | B56: 001 | C56: Bakso Pentol Bang Dimas | D56: Restoran | E56: Jalan H. Gedad, Paninggilan Utara, Ciledug, Tangerang | F56: Paninggilan Utara | G56: Ciledug | H56: Kota Tangerang | I56: Banten | J56: -6.225 | K56: 106.705 | L56: Pusat kelurahan/desa | M56: teks+inferensi | O56: Sempat viral di media sosial, aneka kreasi bakso | Q56: Ya | R56: 0.9 | S56: https://food.detik.com/rumah-makan/d-8550840/7-kuliner-hits-di-ciledug-yang-lagi-viral-ada-nasi-goreng-yang-antre-1-jam | T56: food.detik.com | U56: 7 Kuliner Hits di Ciledug yang Lagi Viral, Ada Nasi Goreng yang Antre 1 Jam! - detikFood | V56: detikFood | W56: 2026-06-28 | X56: Sesuai
A57: 21 | B57: 001 | C57: Festival Kuliner Gang Viral | D57: Pameran | E57: Outdoor Lobby Utama GF, Cambridge City Square, Jl. S. Parman, Medan | F57: Petisah Tengah | G57: Medan Petisah | H57: Kota Medan | I57: Sumatera Utara | J57: 3.583 | K57: 98.665 | L57: Pusat kecamatan | M57: teks+inferensi | N57: Cambridge City Square | O57: Bazar kuliner gang viral Jakarta dengan 40+ tenant viral halal | P57: Minggu, 27 September 2026 | Q57: Ya | R57: 0.9 | S57: https://www.hariansib.com/Kuliner/450454/festival-kuliner-gang-viral-jakarta-hadir-di-medan | T57: www.hariansib.com | U57: Festival Kuliner Gang Viral Jakarta Hadir Di Medan - hariansib.com | V57: hariansib.com | W57: 2026-09-27 | X57: Sesuai
A58: 21 | B58: 001 | C58: Ci Mehong | D58: lainnya | E58: Cambridge City Square, Medan | F58: Petisah Tengah | G58: Medan Petisah | H58: Kota Medan | I58: Sumatera Utara | J58: 3.583 | K58: 98.665 | L58: Pusat kecamatan | M58: teks+inferensi | N58: Cambridge City Square | O58: Populer dengan aksi lempar kaleng | Q58: Ya | R58: 0.6 | S58: https://www.hariansib.com/Kuliner/450454/festival-kuliner-gang-viral-jakarta-hadir-di-medan | T58: www.hariansib.com | U58: Festival Kuliner Gang Viral Jakarta Hadir Di Medan - hariansib.com | V58: hariansib.com | W58: 2026-09-27 | X58: Sesuai
A59: 21 | B59: 001 | C59: PIK Baking House | D59: Kafe | E59: Cambridge City Square, Medan | F59: Petisah Tengah | G59: Medan Petisah | H59: Kota Medan | I59: Sumatera Utara | J59: 3.583 | K59: 98.665 | L59: Pusat kecamatan | M59: teks+inferensi | N59: Cambridge City Square | O59: Produk bika ambon, lapis legit, donat labu | Q59: Tidak | R59: 0.6 | S59: https://www.hariansib.com/Kuliner/450454/festival-kuliner-gang-viral-jakarta-hadir-di-medan | T59: www.hariansib.com | U59: Festival Kuliner Gang Viral Jakarta Hadir Di Medan - hariansib.com | V59: hariansib.com | W59: 2026-09-27 | X59: Sesuai
A60: 22 | B60: 001 | C60: Maevan Cafe | D60: Kafe | E60: Jalan Andi Manappiang RW.05 Biring Kassi, Kelurahan Lembang, Kabupaten Bantaeng, Sulawesi Selatan | F60: Lembang | G60: Bantaeng | H60: Kabupaten Bantaeng | I60: Sulawesi Selatan | J60: -5.55 | K60: 119.95 | L60: Pusat kecamatan | M60: teks+inferensi | O60: Tengah jadi perbincangan hangat, pemandangan sunset dekat Pantai Lamalaka | Q60: Ya | R60: 0.9 | S60: https://lembang-bantaengkab.digitaldesa.id/potensi/-viral-di-bantaeng-maevan-cafe-hadirkan-surga-kuliner-dengan-pesona-sunset-memikat | T60: lembang-bantaengkab.digitaldesa.id | U60: VIRAL DI BANTAENG! MAEVAN CAFE HADIRKAN SURGA KULINER DENGAN PESONA SUNSET MEMIKAT! - Digital Desa | V60: Digital Desa | W60: 2026-09-25 | X60: Sesuai
A61: 22 | B61: 001 | C61: Pantai Lamalaka | D61: Wisata Alam | E61: Bantaeng, Sulawesi Selatan | H61: Kabupaten Bantaeng | I61: Sulawesi Selatan | J61: -5.48 | K61: 119.99 | L61: Pusat kota/kabupaten | M61: teks | O61: Disebut sebagai lokasi dekat Maevan Cafe | Q61: Tidak | R61: 0.5 | S61: https://lembang-bantaengkab.digitaldesa.id/potensi/-viral-di-bantaeng-maevan-cafe-hadirkan-surga-kuliner-dengan-pesona-sunset-memikat | T61: lembang-bantaengkab.digitaldesa.id | U61: VIRAL DI BANTAENG! MAEVAN CAFE HADIRKAN SURGA KULINER DENGAN PESONA SUNSET MEMIKAT! - Digital Desa | V61: Digital Desa | W61: 2026-09-25 | X61: Sesuai
A62: 23 | B62: 001 | C62: Mie Gacoan | D62: Restoran | E62: KS Tubun (gerai terdekat dari Palmerah Selatan), Jakarta | I62: DKI Jakarta | J62: -6.2 | K62: 106.845 | L62: Pusat provinsi | M62: teks+inferensi | N62: Jl. KS Tubun melintasi Jakarta Pusat dan Jakarta Barat | O62: Makanan viral ramah kantong, antrean memanjang | Q62: Ya | R62: 0.8 | S62: https://www.kompas.com/food/read/cm/2026/09/24/104012175/bagaimana-cara-mencari-mie-gacoan-terdekat-dan-kuliner-viral-lain-di | T62: www.kompas.com | U62: Bagaimana Cara Mencari Mie Gacoan Terdekat dan Kuliner Viral Lain di GrabFood? - Kompas.com | V62: Kompas.com | W62: 2026-09-24 | X62: Sesuai
A63: 24 | B63: 001 | C63: Blok M Hub | D63: lainnya | E63: Blok M, Jakarta Selatan | F63: Melawai | G63: Kebayoran Baru | H63: Kota Jakarta Selatan | I63: DKI Jakarta | J63: -6.244 | K63: 106.8 | L63: Titik tempat | M63: teks+inferensi | O63: Spot nongkrong nge-trend, pusat kuliner viral, antre panjang | Q63: Ya | R63: 0.85 | S63: https://www.tripzilla.id/kuliner-blok-m-hub-jakarta/27660 | T63: www.tripzilla.id | U63: 10 Kuliner Viral di Blok M Hub Jakarta, Dari Ayam Pedas Hingga Cimol Keju - tripzilla.id | V63: tripzilla.id | W63: 2026-09-17 | X63: Sesuai
A64: 24 | B64: 001 | C64: Ayam Renald | D64: Restoran | E64: Blok M Hub, Jakarta Selatan | F64: Melawai | G64: Kebayoran Baru | H64: Kota Jakarta Selatan | I64: DKI Jakarta | J64: -6.244 | K64: 106.8 | L64: Titik tempat | M64: teks+inferensi | O64: Kuliner viral milik influencer, olahan ayam aneka bumbu | Q64: Ya | R64: 0.85 | S64: https://www.tripzilla.id/kuliner-blok-m-hub-jakarta/27660 | T64: www.tripzilla.id | U64: 10 Kuliner Viral di Blok M Hub Jakarta, Dari Ayam Pedas Hingga Cimol Keju - tripzilla.id | V64: tripzilla.id | W64: 2026-09-17 | X64: Sesuai
A65: 24 | B65: 001 | C65: Susu Murni Bahagia | D65: Kafe | E65: Blok M Hub, Jakarta Selatan | F65: Melawai | G65: Kebayoran Baru | H65: Kota Jakarta Selatan | I65: DKI Jakarta | J65: -6.244 | K65: 106.8 | L65: Titik tempat | M65: teks+inferensi | O65: Minuman susu viral, buka banyak cabang di Jabodetabek | Q65: Ya | R65: 0.85 | S65: https://www.tripzilla.id/kuliner-blok-m-hub-jakarta/27660 | T65: www.tripzilla.id | U65: 10 Kuliner Viral di Blok M Hub Jakarta, Dari Ayam Pedas Hingga Cimol Keju - tripzilla.id | V65: tripzilla.id | W65: 2026-09-17 | X65: Sesuai
A66: 24 | B66: 001 | C66: Cimol Keju Barito | D66: lainnya | E66: Blok M Hub, Jakarta Selatan | F66: Melawai | G66: Kebayoran Baru | H66: Kota Jakarta Selatan | I66: DKI Jakarta | J66: -6.244 | K66: 106.8 | L66: Titik tempat | M66: teks+inferensi | O66: Cimol isi keju lumer, kuliner viral favorit anak muda | Q66: Ya | R66: 0.8 | S66: https://www.tripzilla.id/kuliner-blok-m-hub-jakarta/27660 | T66: www.tripzilla.id | U66: 10 Kuliner Viral di Blok M Hub Jakarta, Dari Ayam Pedas Hingga Cimol Keju - tripzilla.id | V66: tripzilla.id | W66: 2026-09-17 | X66: Sesuai
A67: 25 | B67: 001 | C67: TikTok Food Fest 2026 | D67: Pameran | E67: Hutan Kota GBK, Jakarta | F67: Gelora | G67: Tanah Abang | H67: Kota Jakarta Pusat | I67: DKI Jakarta | J67: -6.2186 | K67: 106.8019 | L67: Titik tempat | M67: teks+inferensi | N67: Kawasan GBK Senayan | O67: Festival kuliner dengan 40+ tenant makanan viral di TikTok | P67: 26-27 September 2026 | Q67: Ya | R67: 0.9 | S67: https://food.detik.com/pengalaman-bersantap/d-8680372/di-tiktok-food-fest-2026-ada-mochi-gelato-hingga-nasi-lidah-enak | T67: food.detik.com | U67: Di TikTok Food Fest 2026 Ada Mochi Gelato hingga Nasi Lidah Enak - detikFood | V67: detikFood | W67: 2026-09-26 | X67: Sesuai
A68: 25 | B68: 001 | C68: Mad Bagel | D68: Kafe | E68: Tenant TikTok Food Fest, GBK, Jakarta | F68: Gelora | G68: Tanah Abang | H68: Kota Jakarta Pusat | I68: DKI Jakarta | J68: -6.2186 | K68: 106.8019 | L68: Titik tempat | M68: teks+inferensi | N68: Kawasan GBK Senayan | O68: Bagel viral di TikTok | Q68: Ya | R68: 0.85 | S68: https://food.detik.com/pengalaman-bersantap/d-8680372/di-tiktok-food-fest-2026-ada-mochi-gelato-hingga-nasi-lidah-enak | T68: food.detik.com | U68: Di TikTok Food Fest 2026 Ada Mochi Gelato hingga Nasi Lidah Enak - detikFood | V68: detikFood | W68: 2026-09-26 | X68: Sesuai
A69: 25 | B69: 001 | C69: RM Lokiin | D69: Restoran | E69: Blok M, Jakarta | F69: Melawai | G69: Kebayoran Baru | H69: Kota Jakarta Selatan | I69: DKI Jakarta | J69: -6.244 | K69: 106.8 | L69: Titik tempat | M69: teks+inferensi | O69: Viral di Blok M, nasi rames dan nasi lidah | Q69: Ya | R69: 0.85 | S69: https://food.detik.com/pengalaman-bersantap/d-8680372/di-tiktok-food-fest-2026-ada-mochi-gelato-hingga-nasi-lidah-enak | T69: food.detik.com | U69: Di TikTok Food Fest 2026 Ada Mochi Gelato hingga Nasi Lidah Enak - detikFood | V69: detikFood | W69: 2026-09-26 | X69: Sesuai
A70: 25 | B70: 001 | C70: Chuchat | D70: Kafe | E70: Jakarta Barat hingga Tangerang | M70: teks | N70: Beberapa lokasi: Jakarta Barat (DKI Jakarta) hingga Tangerang (Banten) | O70: Milk tea populer | Q70: Tidak | R70: 0.75 | S70: https://food.detik.com/pengalaman-bersantap/d-8680372/di-tiktok-food-fest-2026-ada-mochi-gelato-hingga-nasi-lidah-enak | T70: food.detik.com | U70: Di TikTok Food Fest 2026 Ada Mochi Gelato hingga Nasi Lidah Enak - detikFood | V70: detikFood | W70: 2026-09-26 | X70: Sesuai
A71: 25 | B71: 001 | C71: Fuku | D71: Kafe | E71: Tenant TikTok Food Fest, GBK, Jakarta | F71: Gelora | G71: Tanah Abang | H71: Kota Jakarta Pusat | I71: DKI Jakarta | J71: -6.2186 | K71: 106.8019 | L71: Titik tempat | M71: teks+inferensi | N71: Kawasan GBK Senayan | O71: Dessert gelato mochi kekinian | Q71: Tidak | R71: 0.75 | S71: https://food.detik.com/pengalaman-bersantap/d-8680372/di-tiktok-food-fest-2026-ada-mochi-gelato-hingga-nasi-lidah-enak | T71: food.detik.com | U71: Di TikTok Food Fest 2026 Ada Mochi Gelato hingga Nasi Lidah Enak - detikFood | V71: detikFood | W71: 2026-09-26 | X71: Sesuai
A72: 26 | B72: 001 | C72: Bakmie 96 | D72: Restoran | E72: Jalan Taman Cibeunying Utara, Kota Bandung | F72: Cihapit | G72: Bandung Wetan | H72: Kota Bandung | I72: Jawa Barat | J72: -6.903 | K72: 107.625 | L72: Pusat kelurahan/desa | M72: teks+inferensi | O72: Olahan mi, masuk rekomendasi kuliner viral | Q72: Tidak | R72: 0.8 | S72: https://jabar.antaranews.com/berita/708412/rekomendasi-kuliner-viral-di-sepanjang-jalan-cibeunying-utara-bandung | T72: jabar.antaranews.com | U72: Rekomendasi kuliner viral di sepanjang Jalan Cibeunying Utara Bandung - ANTARA News Jawa Barat | V72: ANTARA News Jawa Barat | W72: 2026-09-22 | X72: Sesuai
A73: 26 | B73: 001 | C73: Dimxie | D73: Restoran | E73: Jalan Taman Cibeunying Utara, Kota Bandung | F73: Cihapit | G73: Bandung Wetan | H73: Kota Bandung | I73: Jawa Barat | J73: -6.903 | K73: 107.625 | L73: Pusat kelurahan/desa | M73: teks+inferensi | O73: Dimsum | Q73: Tidak | R73: 0.8 | S73: https://jabar.antaranews.com/berita/708412/rekomendasi-kuliner-viral-di-sepanjang-jalan-cibeunying-utara-bandung | T73: jabar.antaranews.com | U73: Rekomendasi kuliner viral di sepanjang Jalan Cibeunying Utara Bandung - ANTARA News Jawa Barat | V73: ANTARA News Jawa Barat | W73: 2026-09-22 | X73: Sesuai
A74: 26 | B74: 001 | C74: Gebros | D74: Restoran | E74: Jalan Taman Cibeunying Utara, Kota Bandung | F74: Cihapit | G74: Bandung Wetan | H74: Kota Bandung | I74: Jawa Barat | J74: -6.903 | K74: 107.625 | L74: Pusat kelurahan/desa | M74: teks+inferensi | O74: Gorengan mini seperti gehu cikur dan combro lemet | Q74: Tidak | R74: 0.8 | S74: https://jabar.antaranews.com/berita/708412/rekomendasi-kuliner-viral-di-sepanjang-jalan-cibeunying-utara-bandung | T74: jabar.antaranews.com | U74: Rekomendasi kuliner viral di sepanjang Jalan Cibeunying Utara Bandung - ANTARA News Jawa Barat | V74: ANTARA News Jawa Barat | W74: 2026-09-22 | X74: Sesuai
A75: 26 | B75: 001 | C75: Sate Pak Gito | D75: Restoran | E75: Jalan Taman Cibeunying Utara, Kota Bandung | F75: Cihapit | G75: Bandung Wetan | H75: Kota Bandung | I75: Jawa Barat | J75: -6.903 | K75: 107.625 | L75: Pusat kelurahan/desa | M75: teks+inferensi | O75: Sajian sate | Q75: Tidak | R75: 0.8 | S75: https://jabar.antaranews.com/berita/708412/rekomendasi-kuliner-viral-di-sepanjang-jalan-cibeunying-utara-bandung | T75: jabar.antaranews.com | U75: Rekomendasi kuliner viral di sepanjang Jalan Cibeunying Utara Bandung - ANTARA News Jawa Barat | V75: ANTARA News Jawa Barat | W75: 2026-09-22 | X75: Sesuai
A76: 26 | B76: 001 | C76: Jue Kopi | D76: Kafe | E76: Jalan Taman Cibeunying Utara, Kota Bandung | F76: Cihapit | G76: Bandung Wetan | H76: Kota Bandung | I76: Jawa Barat | J76: -6.903 | K76: 107.625 | L76: Pusat kelurahan/desa | M76: teks+inferensi | O76: Kopi Vietnam | Q76: Tidak | R76: 0.8 | S76: https://jabar.antaranews.com/berita/708412/rekomendasi-kuliner-viral-di-sepanjang-jalan-cibeunying-utara-bandung | T76: jabar.antaranews.com | U76: Rekomendasi kuliner viral di sepanjang Jalan Cibeunying Utara Bandung - ANTARA News Jawa Barat | V76: ANTARA News Jawa Barat | W76: 2026-09-22 | X76: Sesuai
A77: 26 | B77: 001 | C77: Toko Kari | D77: Restoran | E77: Jalan Taman Cibeunying Utara, Kota Bandung | F77: Cihapit | G77: Bandung Wetan | H77: Kota Bandung | I77: Jawa Barat | J77: -6.903 | K77: 107.625 | L77: Pusat kelurahan/desa | M77: teks+inferensi | O77: Kuliner bercita rasa kari | Q77: Tidak | R77: 0.8 | S77: https://jabar.antaranews.com/berita/708412/rekomendasi-kuliner-viral-di-sepanjang-jalan-cibeunying-utara-bandung | T77: jabar.antaranews.com | U77: Rekomendasi kuliner viral di sepanjang Jalan Cibeunying Utara Bandung - ANTARA News Jawa Barat | V77: ANTARA News Jawa Barat | W77: 2026-09-22 | X77: Sesuai
A78: 26 | B78: 001 | C78: Pempek B3doloer | D78: Restoran | E78: Jalan Taman Cibeunying Utara, Kota Bandung | F78: Cihapit | G78: Bandung Wetan | H78: Kota Bandung | I78: Jawa Barat | J78: -6.903 | K78: 107.625 | L78: Pusat kelurahan/desa | M78: teks+inferensi | O78: Pempek khas Palembang | Q78: Tidak | R78: 0.8 | S78: https://jabar.antaranews.com/berita/708412/rekomendasi-kuliner-viral-di-sepanjang-jalan-cibeunying-utara-bandung | T78: jabar.antaranews.com | U78: Rekomendasi kuliner viral di sepanjang Jalan Cibeunying Utara Bandung - ANTARA News Jawa Barat | V78: ANTARA News Jawa Barat | W78: 2026-09-22 | X78: Sesuai
A79: 27 | B79: 001 | C79: RM Sari Moerni | D79: Restoran | E79: Jalan Kisamaun, dekat Pasar Lama, Kota Tangerang | F79: Sukasari | G79: Tangerang | H79: Kota Tangerang | I79: Banten | J79: -6.176 | K79: 106.632 | L79: Pusat kelurahan/desa | M79: teks+inferensi | O79: Destinasi kuliner baru bernuansa Betawi-Sunda, ayam kukus dan es teh kampul | Q79: Tidak | R79: 0.9 | S79: https://tangerangkota.go.id/berita/detail/68715/hadirkan-cita-rasa-betawi-sunda-rm-sari-moerni-jadi-destinasi-kuliner-baru-di-kota-tangerang | T79: tangerangkota.go.id | U79: Hadirkan Cita Rasa Betawi-Sunda, RM Sari Moerni Jadi Destinasi Kuliner Baru di Kota Tangerang - Pemerintah Kota Tangerang | V79: Pemerintah Kota Tangerang | W79: 2026-09-07 | X79: Sesuai
A80: 29 | B80: 001 | C80: Festival Kuliner Nusantarasa by Roadshow Kuliner Viral Indonesia | D80: Pameran | E80: Mal Ratu Indah, Makassar, Sulawesi Selatan | H80: Kota Makassar | I80: Sulawesi Selatan | J80: -5.147 | K80: 119.432 | L80: Pusat kota/kabupaten | M80: teks | N80: Mal Ratu Indah | O80: Festival kuliner viral dengan ratusan menu dan UMKM | P80: 26 Agustus - 6 September 2026 | Q80: Ya | R80: 0.85 | S80: https://www.antarafoto.com/id/view/2850808/festival-kuliner-viral-indonesia-di-makassar | T80: www.antarafoto.com | U80: Festival kuliner viral Indonesia di Makassar - antarafoto.com | V80: antarafoto.com | W80: 2026-08-26 | X80: Sesuai
A81: 31 | B81: 002 | C81: Sop Durian Margando | D81: Kafe | E81: Depok | H81: Kota Depok | I81: Jawa Barat | J81: -6.402 | K81: 106.795 | L81: Pusat kota/kabupaten | M81: teks+inferensi | O81: Ikon kuliner Depok, sop durian dengan durian asli melimpah, hampir selalu ramai; viral lewat food vlogger dan medsos | Q81: Ya | R81: 0.85 | S81: https://chanelmuslim.com/wisata/5-wisata-kuliner-viral-di-depok-yang-wajib-dicoba-dijamin-bikin-ketagihan | T81: chanelmuslim.com | U81: 5 Wisata Kuliner Viral di Depok yang Wajib Dicoba, Dijamin Bikin Ketagihan - Chanelmuslim.com | V81: Chanelmuslim.com | W81: 2026-07-30 | X81: Sesuai
A82: 31 | B82: 002 | C82: Soto Bu Tjondro | D82: Restoran | E82: Depok | H82: Kota Depok | I82: Jawa Barat | J82: -6.402 | K82: 106.795 | L82: Pusat kota/kabupaten | M82: teks+inferensi | O82: Kuah soto gurih kaya rempah; masuk daftar kuliner viral Depok | Q82: Ya | R82: 0.75 | S82: https://chanelmuslim.com/wisata/5-wisata-kuliner-viral-di-depok-yang-wajib-dicoba-dijamin-bikin-ketagihan | T82: chanelmuslim.com | U82: 5 Wisata Kuliner Viral di Depok yang Wajib Dicoba, Dijamin Bikin Ketagihan - Chanelmuslim.com | V82: Chanelmuslim.com | W82: 2026-07-30 | X82: Sesuai
A83: 31 | B83: 002 | C83: Warung Pancong Mang Kumis & Mang Dadang | D83: Kafe | E83: Depok | H83: Kota Depok | I83: Jawa Barat | J83: -6.402 | K83: 106.795 | L83: Pusat kota/kabupaten | M83: teks+inferensi | O83: Mengubah pancong tradisional menjadi kuliner viral | Q83: Ya | R83: 0.85 | S83: https://chanelmuslim.com/wisata/5-wisata-kuliner-viral-di-depok-yang-wajib-dicoba-dijamin-bikin-ketagihan | T83: chanelmuslim.com | U83: 5 Wisata Kuliner Viral di Depok yang Wajib Dicoba, Dijamin Bikin Ketagihan - Chanelmuslim.com | V83: Chanelmuslim.com | W83: 2026-07-30 | X83: Sesuai
A84: 32 | B84: 002 | C84: Blok M | D84: lainnya | E84: Blok M, Jakarta Selatan | F84: Melawai | G84: Kebayoran Baru | H84: Kota Jakarta Selatan | I84: DKI Jakarta | J84: -6.244 | K84: 106.8 | L84: Titik tempat | M84: teks+inferensi | O84: Kawasan kuliner viral yang ramai, destinasi favorit wisman Malaysia | Q84: Ya | R84: 0.8 | S84: https://www.idxchannel.com/ecotainment/kuliner-viral-jadi-daya-tarik-blok-m-masuk-daftar-destinasi-favorit-wisman-malaysia | T84: www.idxchannel.com | U84: Kuliner Viral Jadi Daya Tarik, Blok M Masuk Daftar Destinasi Favorit Wisman Malaysia - IDX Channel | V84: IDX Channel | W84: 2026-09-15 | X84: Tidak sesuai
A85: 33 | B85: 002 | C85: Pasar Cihapit | D85: lainnya | E85: Pasar Cihapit, Kota Bandung | F85: Cihapit | G85: Bandung Wetan | H85: Kota Bandung | I85: Jawa Barat | J85: -6.903 | K85: 107.625 | L85: Pusat kelurahan/desa | M85: teks+inferensi | O85: Destinasi kuliner yang diburu, ramai dibahas di TikTok | Q85: Ya | R85: 0.85 | S85: https://jabar.antaranews.com/berita/707015/rekomendasi-kuliner-viral-pasar-cihapit-bandung-dari-brownies-kunafa-hingga-warung-bu-eha-legendaris | T85: jabar.antaranews.com | U85: Rekomendasi Kuliner Viral Pasar Cihapit Bandung: Dari Brownies Kunafa hingga Warung Bu Eha Legendaris - ANTARA News Jawa Barat | V85: ANTARA News Jawa Barat | W85: 2026-09-14 | X85: Sesuai
A86: 33 | B86: 002 | C86: Brownies Tjihapit | D86: Kafe | E86: Pasar Cihapit, Kota Bandung | F86: Cihapit | G86: Bandung Wetan | H86: Kota Bandung | I86: Jawa Barat | J86: -6.903 | K86: 107.625 | L86: Pusat kelurahan/desa | M86: teks+inferensi | O86: Brownies fudgy varian kunafa pistachio, kuliner yang tengah ramai | Q86: Ya | R86: 0.8 | S86: https://jabar.antaranews.com/berita/707015/rekomendasi-kuliner-viral-pasar-cihapit-bandung-dari-brownies-kunafa-hingga-warung-bu-eha-legendaris | T86: jabar.antaranews.com | U86: Rekomendasi Kuliner Viral Pasar Cihapit Bandung: Dari Brownies Kunafa hingga Warung Bu Eha Legendaris - ANTARA News Jawa Barat | V86: ANTARA News Jawa Barat | W86: 2026-09-14 | X86: Sesuai
A87: 33 | B87: 002 | C87: Rama Ramen | D87: Restoran | E87: Pasar Cihapit, Kota Bandung | F87: Cihapit | G87: Bandung Wetan | H87: Kota Bandung | I87: Jawa Barat | J87: -6.903 | K87: 107.625 | L87: Pusat kelurahan/desa | M87: teks+inferensi | O87: Disebut sebagai penanda lokasi Brownies Tjihapit | Q87: Tidak | R87: 0.5 | S87: https://jabar.antaranews.com/berita/707015/rekomendasi-kuliner-viral-pasar-cihapit-bandung-dari-brownies-kunafa-hingga-warung-bu-eha-legendaris | T87: jabar.antaranews.com | U87: Rekomendasi Kuliner Viral Pasar Cihapit Bandung: Dari Brownies Kunafa hingga Warung Bu Eha Legendaris - ANTARA News Jawa Barat | V87: ANTARA News Jawa Barat | W87: 2026-09-14 | X87: Sesuai
A88: 33 | B88: 002 | C88: Ceu Eha X Dapur Indung | D88: Restoran | E88: Pasar Cihapit, Kota Bandung | F88: Cihapit | G88: Bandung Wetan | H88: Kota Bandung | I88: Jawa Barat | J88: -6.903 | K88: 107.625 | L88: Pusat kelurahan/desa | M88: teks+inferensi | O88: Disebut sebagai penanda lokasi Brownies Tjihapit | Q88: Tidak | R88: 0.5 | S88: https://jabar.antaranews.com/berita/707015/rekomendasi-kuliner-viral-pasar-cihapit-bandung-dari-brownies-kunafa-hingga-warung-bu-eha-legendaris | T88: jabar.antaranews.com | U88: Rekomendasi Kuliner Viral Pasar Cihapit Bandung: Dari Brownies Kunafa hingga Warung Bu Eha Legendaris - ANTARA News Jawa Barat | V88: ANTARA News Jawa Barat | W88: 2026-09-14 | X88: Sesuai
A89: 33 | B89: 002 | C89: Batagor Kahuripan | D89: Restoran | E89: Pasar Cihapit, Kota Bandung | F89: Cihapit | G89: Bandung Wetan | H89: Kota Bandung | I89: Jawa Barat | J89: -6.903 | K89: 107.625 | L89: Pusat kelurahan/desa | M89: teks+inferensi | O89: Batagor legendaris sejak 2007, tengah ramai | Q89: Ya | R89: 0.8 | S89: https://jabar.antaranews.com/berita/707015/rekomendasi-kuliner-viral-pasar-cihapit-bandung-dari-brownies-kunafa-hingga-warung-bu-eha-legendaris | T89: jabar.antaranews.com | U89: Rekomendasi Kuliner Viral Pasar Cihapit Bandung: Dari Brownies Kunafa hingga Warung Bu Eha Legendaris - ANTARA News Jawa Barat | V89: ANTARA News Jawa Barat | W89: 2026-09-14 | X89: Sesuai
A90: 33 | B90: 002 | C90: Toko Kopi Pasar Cihapit (Toko Kopi 1810) | D90: Kafe | E90: Pasar Cihapit, Kota Bandung | F90: Cihapit | G90: Bandung Wetan | H90: Kota Bandung | I90: Jawa Barat | J90: -6.903 | K90: 107.625 | L90: Pusat kelurahan/desa | M90: teks+inferensi | O90: Supplier kopi premium green bean dan roasted bean | Q90: Ya | R90: 0.7 | S90: https://jabar.antaranews.com/berita/707015/rekomendasi-kuliner-viral-pasar-cihapit-bandung-dari-brownies-kunafa-hingga-warung-bu-eha-legendaris | T90: jabar.antaranews.com | U90: Rekomendasi Kuliner Viral Pasar Cihapit Bandung: Dari Brownies Kunafa hingga Warung Bu Eha Legendaris - ANTARA News Jawa Barat | V90: ANTARA News Jawa Barat | W90: 2026-09-14 | X90: Sesuai
A91: 33 | B91: 002 | C91: Warung Nasi Bu Eha | D91: Restoran | E91: Pasar Cihapit, Kota Bandung | F91: Cihapit | G91: Bandung Wetan | H91: Kota Bandung | I91: Jawa Barat | J91: -6.903 | K91: 107.625 | L91: Pusat kelurahan/desa | M91: teks+inferensi | O91: Warung nasi Sunda legendaris sejak 1947, tanpa pengawet | Q91: Ya | R91: 0.85 | S91: https://jabar.antaranews.com/berita/707015/rekomendasi-kuliner-viral-pasar-cihapit-bandung-dari-brownies-kunafa-hingga-warung-bu-eha-legendaris | T91: jabar.antaranews.com | U91: Rekomendasi Kuliner Viral Pasar Cihapit Bandung: Dari Brownies Kunafa hingga Warung Bu Eha Legendaris - ANTARA News Jawa Barat | V91: ANTARA News Jawa Barat | W91: 2026-09-14 | X91: Sesuai
A92: 34 | B92: 002 | C92: Jalan Sabang (Jalan H. Agus Salim) | D92: lainnya | E92: Kebon Sirih, Menteng, Jakarta Pusat | F92: Kebon Sirih | G92: Menteng | H92: Kota Jakarta Pusat | I92: DKI Jakarta | J92: -6.1845 | K92: 106.8265 | L92: Titik tempat | M92: teks+inferensi | O92: Pusat kuliner legendaris, ramai pada malam hari | Q92: Tidak | R92: 0.8 | S92: https://www.tripzilla.id/kuliner-jalan-sabang-murah-legendaris-viral/27681 | T92: www.tripzilla.id | U92: Murah Tapi Melegenda, Kuliner Jalan Sabang Memang Beda! - tripzilla.id | V92: tripzilla.id | W92: 2026-09-19 | X92: Ragu
A93: 35 | B93: 002 | C93: Ketupat Sayur Pasar Lama | D93: Restoran | E93: Pasar Lama dekat Bank BCA, Kota Tangerang | F93: Sukasari | G93: Tangerang | H93: Kota Tangerang | I93: Banten | J93: -6.176 | K93: 106.632 | L93: Pusat kelurahan/desa | M93: teks+inferensi | N93: Kawasan Pasar Lama Tangerang | O93: Menu sarapan favorit yang selalu ramai | Q93: Tidak | R93: 0.85 | S93: https://www.tangerangkota.go.id/berita/detail/67479/cari-sarapan-enak-di-kota-tangerang-ini-rekomendasi-tempatnya | T93: www.tangerangkota.go.id | U93: Cari Sarapan Enak di Kota Tangerang? Ini Rekomendasi Tempatnya - Pemerintah Kota Tangerang | V93: Pemerintah Kota Tangerang | W93: 2026-07-31 | X93: Sesuai
A94: 35 | B94: 002 | C94: Soto Benteng Bang Udin | D94: Restoran | E94: Jalan Saham, Kelurahan Sukasari, Kecamatan Tangerang, Kota Tangerang | F94: Sukasari | G94: Tangerang | H94: Kota Tangerang | I94: Banten | J94: -6.176 | K94: 106.632 | L94: Pusat kelurahan/desa | M94: teks+inferensi | O94: Soto khas Tangerang dengan daging dan jeroan dibakar | Q94: Tidak | R94: 0.85 | S94: https://www.tangerangkota.go.id/berita/detail/67479/cari-sarapan-enak-di-kota-tangerang-ini-rekomendasi-tempatnya | T94: www.tangerangkota.go.id | U94: Cari Sarapan Enak di Kota Tangerang? Ini Rekomendasi Tempatnya - Pemerintah Kota Tangerang | V94: Pemerintah Kota Tangerang | W94: 2026-07-31 | X94: Sesuai
A95: 35 | B95: 002 | C95: Bubur Ayam Spesial Ko Iyo | D95: Restoran | E95: Kawasan Pasar Lama, Kota Tangerang | F95: Sukasari | G95: Tangerang | H95: Kota Tangerang | I95: Banten | J95: -6.176 | K95: 106.632 | L95: Pusat kelurahan/desa | M95: teks+inferensi | N95: Kawasan Pasar Lama Tangerang | O95: Bubur ayam banyak diburu dengan pelengkap lengkap | Q95: Tidak | R95: 0.85 | S95: https://www.tangerangkota.go.id/berita/detail/67479/cari-sarapan-enak-di-kota-tangerang-ini-rekomendasi-tempatnya | T95: www.tangerangkota.go.id | U95: Cari Sarapan Enak di Kota Tangerang? Ini Rekomendasi Tempatnya - Pemerintah Kota Tangerang | V95: Pemerintah Kota Tangerang | W95: 2026-07-31 | X95: Sesuai
A96: 35 | B96: 002 | C96: Bubur Ayam Mas Yanto | D96: Restoran | E96: Jalan Kasasi Raya Blok C10 No.1, Komplek Pengayoman, Sukasari, Kota Tangerang | F96: Sukasari | G96: Tangerang | H96: Kota Tangerang | I96: Banten | J96: -6.176 | K96: 106.632 | L96: Pusat kelurahan/desa | M96: teks+inferensi | O96: Bubur ayam legendaris sejak 1970 | Q96: Tidak | R96: 0.85 | S96: https://www.tangerangkota.go.id/berita/detail/67479/cari-sarapan-enak-di-kota-tangerang-ini-rekomendasi-tempatnya | T96: www.tangerangkota.go.id | U96: Cari Sarapan Enak di Kota Tangerang? Ini Rekomendasi Tempatnya - Pemerintah Kota Tangerang | V96: Pemerintah Kota Tangerang | W96: 2026-07-31 | X96: Sesuai
A97: 35 | B97: 002 | C97: Mie Ayam Bangka Asen | D97: Restoran | E97: Perumahan Banjar Wijaya, Kecamatan Cipondoh, Kota Tangerang | G97: Cipondoh | H97: Kota Tangerang | I97: Banten | J97: -6.185 | K97: 106.69 | L97: Pusat kecamatan | M97: teks+inferensi | O97: Mi ayam Bangka | Q97: Tidak | R97: 0.8 | S97: https://www.tangerangkota.go.id/berita/detail/67479/cari-sarapan-enak-di-kota-tangerang-ini-rekomendasi-tempatnya | T97: www.tangerangkota.go.id | U97: Cari Sarapan Enak di Kota Tangerang? Ini Rekomendasi Tempatnya - Pemerintah Kota Tangerang | V97: Pemerintah Kota Tangerang | W97: 2026-07-31 | X97: Sesuai
A98: 37 | B98: 002 | C98: Pure Amboina | D98: Kafe | E98: Kota Ambon | H98: Kota Ambon | I98: Maluku | J98: -3.695 | K98: 128.181 | L98: Pusat kota/kabupaten | M98: teks+inferensi | O98: UMKM cold-pressed juice tanpa gula dan pengawet | Q98: Tidak | R98: 0.6 | S98: https://rri.co.id/ambon/ekonomi/umkm/2725229/gaya-hidup-sehat-kuliner-viral-3-umkm-ambon-bagikan-rahasia-sukses | T98: rri.co.id | U98: Gaya Hidup Sehat, Kuliner Viral, 3 UMKM Ambon Bagikan Rahasia Sukses - RRI.co.id | V98: RRI.co.id | W98: 2026-09-13 | X98: Sesuai
A99: 37 | B99: 002 | C99: Fresh Lemora | D99: Kafe | E99: Kota Ambon | H99: Kota Ambon | I99: Maluku | J99: -3.695 | K99: 128.181 | L99: Pusat kota/kabupaten | M99: teks+inferensi | O99: Smoothies instagramable untuk Gen Z | Q99: Tidak | R99: 0.6 | S99: https://rri.co.id/ambon/ekonomi/umkm/2725229/gaya-hidup-sehat-kuliner-viral-3-umkm-ambon-bagikan-rahasia-sukses | T99: rri.co.id | U99: Gaya Hidup Sehat, Kuliner Viral, 3 UMKM Ambon Bagikan Rahasia Sukses - RRI.co.id | V99: RRI.co.id | W99: 2026-09-13 | X99: Sesuai
A100: 37 | B100: 002 | C100: John House | D100: Restoran | E100: Kota Ambon | H100: Kota Ambon | I100: Maluku | J100: -3.695 | K100: 128.181 | L100: Pusat kota/kabupaten | M100: teks+inferensi | O100: Populer di TikTok lewat Roti John isian khas Maluku | Q100: Ya | R100: 0.75 | S100: https://rri.co.id/ambon/ekonomi/umkm/2725229/gaya-hidup-sehat-kuliner-viral-3-umkm-ambon-bagikan-rahasia-sukses | T100: rri.co.id | U100: Gaya Hidup Sehat, Kuliner Viral, 3 UMKM Ambon Bagikan Rahasia Sukses - RRI.co.id | V100: RRI.co.id | W100: 2026-09-13 | X100: Sesuai
...

Sheet Artikel
A1: article_id | B1: batch | C1: jumlah_tempat | D1: jumlah_viral_eksplisit | E1: final_url (sumber isi) | F1: domain URL | G1: judul (id_map) | H1: source (id_map) | I1: published (id_map) | J1: cuplikan isi | K1: judul sesuai isi? | L1: skor judul vs isi | M1: skor URL vs isi
A2: 0 | B2: 001 | C2: 0 | D2: 0 | E2: https://jatimnet.com/media-sosial-mengubah-cara-kita-memilih-tempat-makan | F2: jatimnet.com | G2: Media Sosial Mengubah Cara Kita Memilih Tempat Makan - Jatimnet.com | H2: Jatimnet.com | I2: 2026-09-25 | J2: Jumat, 25 September 2026 08:00 UTC Ilustrasi: Pilihan dari Layar. -Dx Gen-AI JATIMNET.COM - Media sosial mengubah cara memilih tempat makan dalam kehidupan sehari-hari. Restoran yang sebelumnya ditemu | K2: Sesuai | L2: 0.88 | M2: 0.88
A3: 1 | B3: 001 | C3: 4 | D3: 0 | E3: https://food.detik.com/rumah-makan/d-8679688/awas-kalap-ini-7-tempat-makan-soto-mie-legendaris-di-jakarta-dan-bogor | F3: food.detik.com | G3: Awas Kalap! Ini 7 Tempat Makan Soto Mie Legendaris di Jakarta dan Bogor - detikFood | H3: detikFood | I3: 2026-09-26 | J3: Di Jakarta dan Bogor, ada kedai soto mie yang sudah buka sejak puluhan tahun lalu dan terkenal lezat. Bahkan sampai sekarang masih terus diburu oleh pelanggannya. Soto mie menjadi salah satu hidangan | K3: Sesuai | L3: 0.67 | M3: 0.6
A4: 2 | B4: 001 | C4: 2 | D4: 0 | E4: https://rri.co.id/yogyakarta/kuliner/2752639/rekomendasi-7-tempat-makan-ramah-kantong-di-jogja-dan-tips-menggunakan-grabfood | F4: rri.co.id | G4: Rekomendasi 7 Tempat Makan Ramah Kantong di Jogja dan Tips Menggunakan GrabFood - RRI.co.id | H4: RRI.co.id | I4: 2026-09-23 | J4: RRI.CO.ID, Yogyakarta - Daerah Istimewa Yogyakarta (DIY).dikenal luas sebagai surganya kuliner murah di Indonesia, tempat menikmati hidangan otentik Jawa hingga sajian internasional tanpa menguras dom | K4: Sesuai | L4: 0.78 | M4: 0.82
A5: 3 | B5: 001 | C5: 2 | D5: 2 | E5: https://www.nibble.id/tempat-makan-viral-di-bandung-2026/ | F5: www.nibble.id | G5: 10 Tempat Makan Viral di Bandung 2026 - nibble.id | H5: nibble.id | I5: 2026-06-09 | J5: Harus siapkan mental buat antre, ini dia tempat makan viral di Bandung 2026 yang sampai kini selalu gak ada habisnya dibahas. Kota ini memang gak ada hentinya untuk memunculkan banyak spot kulineran e | K5: Sesuai | L5: 1 | M5: 1
A6: 4 | B6: 001 | C6: 8 | D6: 8 | E6: https://aktualita.co/ragam/tiktok-food-fest-2026-hari-terakhir-gbk | F6: aktualita.co | G6: TikTok Food Fest 2026 Hari Terakhir di GBK, Ada 40 Lebih Tenant hingga Kuliner Viral - Aktualita.co | H6: Aktualita.co | I6: 2026-09-27 | J6: English edition available TikTok Food Fest 2026 Hari Terakhir di GBK, Ada 40 Lebih Tenant hingga Kuliner Viral Jakarta , Aktualita.co — TikTok Food Fest 2026 memasuki hari terakhir penyelenggaraan pad | K6: Sesuai | L6: 1 | M6: 0.86
A7: 5 | B7: 001 | C7: 3 | D7: 0 | E7: https://www.tripzilla.id/tempat-makan-di-bekasi-hits-legendaris-dan-ramah-kantong/27718 | F7: www.tripzilla.id | G7: Buat YTTA, Tempat Makan Di Bekasi Bikin Orang Jakarta Rela Antre! - tripzilla.id | H7: tripzilla.id | I7: 2026-09-22 | J7: Sebagai seorang travel writer yang hobi keliling berburu kuliner, Bekasi sering kali mengejutkan saya! Kota yang sering dituduh "berada di luar planet" ini ternyata menyimpan surga kuliner yang sangat | K7: Ragu | L7: 0.44 | M7: 0.43
A8: 6 | B8: 001 | C8: 1 | D8: 0 | E8: https://jogja.disway.id/gaya-hidup/read/702022/deretan-warung-ayam-goreng-legendaris-paling-hits-di-purwokerto-dengan-cita-rasa-rempah | F8: jogja.disway.id | G8: Deretan Warung Ayam Goreng Legendaris Paling Hits di Purwokerto dengan Cita Rasa Rempah - jogja.disway.id - Disway Jogja | H8: Disway Jogja | I8: 2026-09-27 | J8: Ayam Goreng Kalibogor-- diswayjogja.id - Dunia kuliner tradisional di Kota Purwokerto terus menunjukkan pesona yang sangat kuat dan memukau, ditandai dengan tetap eksisnya berbagai warung serta rumah | K8: Sesuai | L8: 0.62 | M8: 0.77
A9: 7 | B9: 001 | C9: 2 | D9: 0 | E9: https://jatim.idntimes.com/food/dining-guide/10-rekomendasi-kuliner-malam-di-sidoarjo-cocok-bagi-pencinta-kuliner-c1c2-01-njfwj-gnsrbz | F9: jatim.idntimes.com | G9: 10 Rekomendasi Kuliner Malam Sidoarjo, Gak Takut Lapar Saat Begadang - IDN Times Jatim | H9: IDN Times Jatim | I9: 2026-09-16 | J9: Kuliner malam di Sidoarjo menjadi daya tarik tersendiri bagi masyarakat Jawa Timur. Berbagai warung makan, kaki lima, hingga restoran tetap ramai dikunjungi saat malam hari. Perpaduan antara sajian ya | K9: Sesuai | L9: 0.5 | M9: 0.46
A10: 8 | B10: 001 | C10: 5 | D10: 0 | E10: https://www.rumah123.com/explore/kota-jakarta-timur/tempat-makan-di-jakarta-timur-yang-murah-dan-enak/ | F10: www.rumah123.com | G10: 7 Rekomendasi Tempat Makan di Jakarta Timur yang Murah dan Enak - rumah123.com | H10: rumah123.com | I10: 2026-04-18 | J10: Mencari tempat makan di Jakarta Timur yang murah dan enak bukan hal sulit. Kawasan ini punya banyak pilihan, mulai dari warung sederhana hingga restoran keluarga dengan harga yang masih ramah di kanto | K10: Sesuai | L10: 1 | M10: 0.75
A11: 9 | B11: 001 | C11: 3 | D11: 0 | E11: https://erafone.com/artikel/post/wisata-kuliner-malang-04 | F11: erafone.com | G11: 10 Rekomendasi Destinasi Wisata Kuliner Malang yang Enak - Erafone | H11: Erafone | I11: 2026-08-18 | J11: Malang tidak hanya terkenal dengan deretan tempat wisata dan lingkungan udaranya yang sejuk. Kota ini juga punya surga kuliner yang akan memanjakan perut kamu, mulai dari bakso legendaris, rawon denga | K11: Sesuai | L11: 1 | M11: 1
A12: 10 | B12: 001 | C12: 2 | D12: 0 | E12: https://www.hipwee.com/travel/tempat-makan-murah-di-tangerang/ | F12: www.hipwee.com | G12: 8 Tempat Makan Murah di Tangerang yang Enak dan Bikin Kenyang - Hipwee | H12: Hipwee | I12: 2026-07-22 | J12: Berburu tempat makan di Tangerang sebenarnya nggak terlalu sulit karena pilihannya melimpah. Mulai dari area Pasar Lama yang padat kuliner legendaris sampai sudut-sudut BSD, selalu ada pilihan tempat | K12: Sesuai | L12: 0.71 | M12: 0.8
A13: 11 | B13: 001 | C13: 1 | D13: 0 | E13: https://rri.co.id/madiun/kuliner/2758486/harmadha-joglo-tempat-kuliner-hits-magetan | F13: rri.co.id | G13: Harmadha Joglo, Tempat Kuliner Hits Magetan - RRI.co.id | H13: RRI.co.id | I13: 2026-09-25 | J13: RRI.CO.ID, Madiun - Siapa sih yang tidak kenal Harmadha Joglo? Salah satu restoran sekaligus tempat nongkrong yang cukup terkenal di Magetan ini selalu menjadi pilihan bagi masyarakat yang ingin menik | K13: Sesuai | L13: 0.83 | M13: 0.86
... A75: 73 | B75: 003 | C75: 0 | D75: 0 | E75: https://gotvnews.co.id/viral-kasatpol-pp-samarinda-cekcok-dengan-anggota-tni-saat-penertiban-warung-miras/ | F75: gotvnews.co.id | G75: Viral, Kasatpol PP Samarinda Cekcok Dengan Anggota TNI Saat Penertiban Warung Miras - gotvnews.co.id | H75: gotvnews.co.id | I75: 2026-09-24 | J75: GOTVNEWS, Kaltim – Penertiban sejumlah warung yang diduga menjadi lokasi penjualan minuman keras di Jalan Teuku Umar, Samarinda, Kalimantan Timur, Selasa (22/9/2026) malam, sempat diwarnai cekcok anta | K75: Sesuai | L75: 0.75 | M75: 0.75
A76: 74 | B76: 003 | C76: 0 | D76: 0 | E76: https://www.mcwnews.com | F76: www.mcwnews.com | G76: Duo WN Iran Viral Hipnotis Pedagang Warung Ditangkap di Kuta - mcwnews.com | H76: mcwnews.com | I76: 2026-09-22 | J76: Kejari Mimika Tetapkan Tersangka Korupsi Pembangunan Gerai Maritim Kejagung Tetapkan 5 Tersangka Korupsi Tata Kelola Nikel, Kerugian Negara Rp401,65 Miliar DPO Korupsi Kejati Kalsel Ditangkap di Berau | K76: Tidak sesuai | L76: 0.14
A77: 75 | B77: 003 | C77: 0 | D77: 0 | E77: https://radarbadung.jawapos.com/bali/2609160004/ngaku-pecalang-pungut-rp120-ribu-di-warung-warga-gianyar-viral-di-tiktok | F77: radarbadung.jawapos.com | G77: Ngaku Pecalang Pungut Rp120 Ribu di Warung, Warga Gianyar Viral di TikTok - Radar Badung | H77: Radar Badung | I77: 2026-09-16 | J77: Aksi pria mengaku sebagai Pecalang dan meminta uang keamanan serta iuran banjar di sebuah warung makan di Jalan Gunung Soputan, Denpasar, viral di media sosial TikTok. | K77: Ragu | L77: 0.33 | M77: 0.3
A78: 76 | B78: 003 | C78: 0 | D78: 0 | E78: https://news.detik.com/berita/d-8643188/viral-pemotor-dikejar-begal-sampai-nabrak-warung-di-tebet-polisi-selidiki | F78: news.detik.com | G78: Viral Pemotor Dikejar Begal Sampai Nabrak Warung di Tebet, Polisi Selidiki - detikNews | H78: detikNews | I78: 2026-09-01 | J78: Rekaman CCTV yang menunjukkan dugaan pembegalan terhadap dua orang pemuda di Tebet, Jakarta Selatan (Jaksel), viral di media sosial. Polisi menduga korban dan pelaku diduga saling kenal. Dalam video y | K78: Sesuai | L78: 0.56 | M78: 0.56
A79: 77 | B79: 003 | C79: 0 | D79: 0 | E79: https://depok.tribunnews.com/news/52323/viral-penyerangan-pelajar-di-duren-sawit-korban-ditebas-sajam-warung-jadi-sasaran-amuk-pelaku | F79: depok.tribunnews.com | G79: Viral Penyerangan Pelajar di Duren Sawit: Korban Ditebas Sajam, Warung Jadi Sasaran Amuk Pelaku - Tribunnewsdepok.com | H79: Tribunnewsdepok.com | I79: 2026-09-13 | J79: Belum punya akun? Daftar Akun Download TribunX untuk Android & iOS TRIBUNNEWSDEPOK.COM, JAKARTA TIMUR – Jagat media sosial dihebohkan oleh rekaman video aksi penyerangan brutal sekelompok pelajar berm | K79: Sesuai | L79: 0.73 | M79: 0.73
A80: 78 | B80: 003 | C80: 0 | D80: 0 | E80: https://www.suryaindonesia.net/2026/09/10/viral-di-media-sosial-terkait-dugaan-aksi-penipuan-yang-melibatkan-seorang-warga-negara-asing-wna-di-sebuah-warung-wilayah-darmasaba/ | F80: www.suryaindonesia.net | G80: Viral di Media Sosial terkait dugaan aksi penipuan yang melibatkan seorang warga negara asing (WNA) di sebuah warung wilayah Darmasaba - suryaindonesia.net | H80: suryaindonesia.net | I80: 2026-09-10 | J80: Redaksi Surya Indonesia Kamis, 10 September 2026 - 16:18 WIB Mangupura, Surya Indonesia.net – Menindaklanjuti informasi yang Viral di Media Sosial terkait dugaan aksi penipuan yang melibatka | K80: Sesuai | L80: 1 | M80: 1
A81: 79 | B81: 003 | C81: 1 | D81: 1 | E81: https://carapandang.com/news/read/warung-di-tengah-makam-viral-ulama-tegaskan-kuburan-muslim-harus-dijaga-kehormatannya | F81: carapandang.com | G81: Warung di Tengah Makam Viral, Ulama Tegaskan Kuburan Muslim Harus Dijaga Kehormatannya - CaraPandang | H81: CaraPandang | I81: 2026-07-24 | J81: CARAPANDANG – Sebuah warung makan yang berdiri di tengah kompleks pemakaman di Karawang, Jawa Barat, menjadi perhatian publik. Lokasinya yang tidak lazim membuat banyak orang penasaran hingga rela dat | K81: Ragu | L81: 0.4 | M81: 0.4
A82: 80 | B82: 003 | C82: 1 | D82: 1 | E82: https://regional.kompas.com/read/2026/07/17/183019078/viral-warung-lontong-di-pati-ditarik-retribusi-rp-840000-dputr-bukan-tarif?page=all | F82: regional.kompas.com | G82: Viral Warung Lontong di Pati Ditarik Retribusi Rp 840.000, DPUTR: Bukan Tarif Setahun - Kompas.com | H82: Kompas.com | I82: 2026-07-17 | J82: Viral Warung Lontong di Pati Ditarik Retribusi Rp 840.000, DPUTR: Bukan Tarif Setahun PATI, KOMPAS.com – Video seorang pemilik warung lontong sayur di Desa Kebolampang, Kecamatan Winong, Kabupaten Pat | K82: Sesuai | L82: 1 | M82: 1
A83: 81 | B83: 003 | C83: 1 | D83: 0 | E83: https://timesindonesia.co.id/kuliner/601107/tidak-viral-tapi-warung-ini-punya-menu-andalan-yang-bikin-pelanggan-rela-balik-lagi | F83: timesindonesia.co.id | G83: Tidak Viral, Tapi Warung ini Punya Menu Andalan yang Bikin Pelanggan Rela Balik Lagi - TIMES Indonesia | H83: TIMES Indonesia | I83: 2026-07-28 | J83: BATU – Di tengah menjamurnya tempat kuliner dengan konsep kekinian, sebuah warung sederhana di Kota Batu justru mencuri perhatian lewat cara berbeda. Tidak mengandalkan promosi besar di media sosial, | K83: Ragu | L83: 0.45 | M83: 0.5
A84: 82 | B84: 003 | C84: 0 | D84: 0 | E84: https://gotvnews.co.id/viral-dua-pria-terlibat-perkelahian-di-warung-kopi-tanjungpinang-diduga-berawal-saling-senggol/ | F84: gotvnews.co.id | G84: Viral! Dua Pria Terlibat Perkelahian di Warung Kopi Tanjungpinang, Diduga Berawal Saling Senggol - gotvnews.co.id | H84: gotvnews.co.id | I84: 2026-09-21 | J84: GOTVNEWS, Tanjungpinang – Video dua pria terlibat perkelahian di sebuah warung kopi di kawasan Bakar Batu, Kota Tanjungpinang, viral di media sosial, Senin (21/9/2026). Dalam video yang beredar, seora | K84: Sesuai | L84: 0.91 | M84: 0.91
A85: 83 | B85: 003 | C85: 1 | D85: 1 | E85: https://food.detik.com/info-kuliner/d-8649807/viral-bebi-romeo-hobi-makan-mie-ayam-warung-makan-ini-jadi-favorit | F85: food.detik.com | G85: Viral! Bebi Romeo Hobi Makan Mie Ayam, Warung Makan Ini Jadi Favorit - detikFood | H85: detikFood | I85: 2026-09-05 | J85: Bebi Romeo diketahui hobi membagikan momen saat menikmati mie ayam favoritnya di kawasan Fatmawati, Jakarta Selatan. Berikut nama warung makan dan racikan favoritnya! Mie ayam memang digemari banyak o | K85: Sesuai | L85: 1 | M85: 0.8
A86: 84 | B86: 003 | C86: 0 | D86: 0 | E86: https://news.detik.com/berita/d-8577814/bang-jago-bersajam-viral-bikin-onar-di-warung-jamu-bogor-ditangkap | F86: news.detik.com | G86: Bang Jago Bersajam Viral Bikin Onar di Warung Jamu Bogor Ditangkap - detikNews | H86: detikNews | I86: 2026-07-17 | J86: Pria yang membawa golok dan membuat onar di warung jamu kawasan Kamurang, Kecamatan Citeureup, Bogor , Jawa Barat, ditangkap. Pelaku berinisial IK (18). "Polsek Citeureup bersama Tim Resmob Polres Bog | K86: Sesuai | L86: 0.89 | M86: 0.89
A87: 85 | B87: 003 | C87: 0 | D87: 0 | E87: https://20.detik.com/detikupdate/20260730-260730011/video-viral-sekelompok-pemuda-bawa-celurit-serang-warung-makan-di-sidoarjo | F87: 20.detik.com | G87: Video Viral Sekelompok Pemuda Bawa Celurit Serang Warung Makan di Sidoarjo - 20detik | H87: 20detik | I87: 2026-07-30 | J87: Scroll atau gunakan tombol [ ] [ ] serta klik panah di sisi kanan untuk menjelajahi feed video. Viral sekelompok pemud | K87: Sesuai | L87: 0.56 | M87: 0.5
A88: 86 | B88: 003 | C88: 0 | D88: 0 | E88: https://news.detik.com/berita/d-8573022/viral-bang-jago-bersajam-bikin-onar-di-warung-jamu-bogor-polisi-selidiki | F88: news.detik.com | G88: Viral Bang Jago Bersajam Bikin Onar di Warung Jamu Bogor, Polisi Selidiki - detikNews | H88: detikNews | I88: 2026-07-14 | J88: Video seorang pria membuat onar di sebuah warung jamu kawasan Kamurang, Kecamatan Citeureup, Bogor , Jawa Barat, beredar di media sosial. Pria tersebut tampak membawa senjata tajam. Dalam video yang d | K88: Sesuai | L88: 0.6 | M88: 0.6
... A140: 138 | B140: 005 | C140: 1 | D140: 0 | E140: https://swa.co.id/read/471273/destinasi-wisata-baru-di-jogja-ini-6-hal-yang-ditawarkan-di-ibarbo-park | F140: swa.co.id | G140: Destinasi Wisata Baru di Jogja, Ini 6 Hal yang Ditawarkan Di Ibarbo Park! - SWA.co.id | H140: SWA.co.id | I140: 2026-04-10 | J140: Dilarang keras mengambil konten (tulisan, foto, infografis, video, dan sebagainya) yang dimuat di situs web ini, melakukan crawling atau pengindeksan otomatis untuk p | K140: Tidak sesuai | L140: 0 | M140: 0
A141: 139 | B141: 005 | C141: 1 | D141: 1 | E141: https://nativeindonesia.com/mikutopia-batu/ | F141: nativeindonesia.com | G141: Mikutopia Batu, Surga Wisata Baru yang Lagi Viral di Malang - NativeIndonesia.com | H141: NativeIndonesia.com | I141: 2026-04-03 | J141: Nativeindonesia – Popularitas Mikutopia Batu semakin melejit berkat media sosial. Banyak pengunjung yang membagikan momen seru mereka saat berada di lokasi ini, mulai dari spot foto yang estetik hingg | K141: Sesuai | L141: 0.83
A142: 140 | B142: 005 | C142: 4 | D142: 4 | E142: https://chanelmuslim.com/wisata/viral-canyoning-banyak-digemari-kalangan-muda-dan-jadi-destinasi-baru-di-bogor | F142: chanelmuslim.com | G142: Viral, Canyoning Banyak Digemari Kalangan Muda dan Jadi Destinasi Baru di Bogor - Chanelmuslim.com | H142: Chanelmuslim.com | I142: 2026-08-24 | J142: <strong>BOGOR</strong> kembali menghadirkan destinasi wisata baru yang tengah viral di kalangan muda, yakni Canyoning Bogor. Aktivitas ekstrem yang memadukan petualangan alam dan olahraga ini kini men | K142: Sesuai | L142: 1 | M142: 1
A143: 141 | B143: 005 | C143: 6 | D143: 1 | E143: https://radarsukabumi.com/wisata/10-tempat-wisata-hits-di-sukabumi-2026-yang-wajib-masuk-bucket-list-kamu/ | F143: radarsukabumi.com | G143: 10 Tempat Wisata Hits di Sukabumi 2026 yang Wajib Masuk Bucket List Kamu! - radarsukabumi.com | H143: radarsukabumi.com | I143: 2026-06-20 | J143: Biar kalian nggak kudet, yuk simak 10 tempat wisata favorit di Sukabumi terbaru tahun 2026 yang wajib kalian datangi bareng geng atau pacar: 1. Goalpara Tea Park (GTP) Bukan cuma kebun teh biasa, temp | K143: Sesuai | L143: 0.56 | M143: 0.56
A144: 142 | B144: 005 | C144: 1 | D144: 1 | E144: https://www.detik.com/jatim/wisata/d-8429886/5-fakta-uji-coba-berbahaya-mikutopia-pengunjung-tewas-wahana-patah | F144: www.detik.com | G144: 5 Fakta Uji Coba Berbahaya Mikutopia: Pengunjung Tewas-Wahana Patah - detikcom | H144: detikcom | I144: 2026-04-05 | J144: Destinasi wisata baru Mikutopia di Kecamatan Bumiaji, Kota Batu, mendadak viral. Namun bukan karena keindahan atau daya tariknya, melainkan serangkaian insiden yang memicu kekhawatiran publik. Dalam w | K144: Sesuai | L144: 0.78 | M144: 0.73
A145: 143 | B145: 005 | C145: 1 | D145: 1 | E145: https://tv.sinpo.id/detail/museum-anti-stres-viral-di-china | F145: tv.sinpo.id | G145: Museum Anti Stres Viral di China - SinPo.id | H145: SinPo.id | I145: 2026-06-09 | J145: SinPo.tv - Sebuah museum unik di Kota Shenzhen, China, menarik perhatian pengunjung dengan berbagai instalasi seni nyeleneh yang menyindir tekanan hidup modern dan budaya kerja saat ini. 30 Agustus 20 | K145: Sesuai | L145: 0.5 | M145: 0.5
A146: 144 | B146: 005 | C146: 1 | D146: 1 | E146: https://jogja.times.co.id/news/wisata/YF3oMMsA/gratis-plus-viral-museum-terumbu-karang-indonesia-sajikan-pesona-bawah-laut | F146: jogja.times.co.id | G146: Gratis plus Viral, Museum Terumbu Karang Indonesia Sajikan Pesona Bawah Laut - TIMES Jogja | H146: TIMES Jogja | I146: 2026-07-10 | J146: Museum Terumbu Karang Indonesia menawarkan pengalaman menjelajahi ekosistem laut Indonesia tanpa harus basah-basahan. JOGJA – Siapa bilang menikmati keindahan bawah laut harus pergi ke pantai atau men | K146: Sesuai | L146: 0.8 | M146: 0.75
A147: 145 | B147: 005 | C147: 0 | D147: 0 | E147: https://jogja.disway.id/wisata/read/700045/cara-baru-keliling-museum-dengan-koleksi-cap-estetik-dengan-museum-passport-yang-viral | F147: jogja.disway.id | G147: Cara Baru Keliling Museum dengan Koleksi Cap Estetik dengan Museum Passport yang Viral - jogja.disway.id - Disway Jogja | H147: Disway Jogja | I147: 2026-07-01 | J147: Museum Passport yang Viral-- diswayjogja.id - Bagi banyak orang, mengunjungi museum mungkin dianggap sebagai kegiatan yang monoton dan kaku. Namun, narasi tersebut perlahan berubah sejak kehadiran Mus | K147: Ragu | L147: 0.44 | M147: 0.62
A148: 146 | B148: 005 | C148: 1 | D148: 1 | E148: https://mimbarrakyatnews.com/art-dialogue-ii-viral-dan-antrean-panjang-di-tasikmalaya-galeri-belum-buka-kang-acong-monolog/ | F148: mimbarrakyatnews.com | G148: Art dialogue II viral dan antrean panjang di Tasikmalaya: galeri belum buka, kang acong monolog - mimbarrakyatnews.com | H148: mimbarrakyatnews.com | I148: 2026-08-01 | J148: Antrean panjang sudah mengular di depan galeri sebelum pintu resmi dibuka untuk Art Dialogue II di Tasikmalaya , sebuah kejadian yang jadi bahan perbincangan setelah video singkat beredar di media sos | K148: Sesuai | L148: 0.73 | M148: 0.73
A149: 147 | B149: 005 | C149: 0 | D149: 0 | E149: https://metropolitan.jawapos.com/metropolitan/2604080001/5-galeri-dan-art-space-di-jakarta-ini-sering-gelar-pameran-gratis-dan-terbuka-untuk-umum | F149: metropolitan.jawapos.com | G149: 5 Galeri dan Art Space di Jakarta Ini Sering Gelar Pameran Gratis dan Terbuka untuk Umum - Jawa Pos Metropolitan | H149: Jawa Pos Metropolitan | I149: 2026-04-08 | J149: Hadirnya berbagai galeri dan art space sebagai ruang apresiasi untuk seni dan para seniman di belakangnya. Menariknya, beberapa tempat tersebut rutin menggelar pameran yang terbuka untuk umum secara g | K149: Sesuai | L149: 0.7 | M149: 0.64
A150: 148 | B150: 005 | C150: 0 | D150: 0 | E150: https://afederasi.com/golkar-tulungagung-kritik-minimnya-fasilitas-kesenian-dorong-pembangunan-galeri-seni | F150: afederasi.com | G150: Golkar Tulungagung Kritik Minimnya Fasilitas Kesenian, Dorong Pembangunan Galeri Seni - Afederasi | H150: Afederasi | I150: 2026-06-08 | J150: Join our subscribers list to get the latest news, updates and special offers directly in your inbox Tulungagung, (afederasi.com) – Partai Golkar Tulungagung menyoroti perlunya penguatan ekosistem seni | K150: Sesuai | L150: 0.7 | M150: 0.7
A151: 149 | B151: 005 | C151: 0 | D151: 0 | E151: https://bekasi.inews.id/read/714544/viral-keributan-di-mal-bekasi-utara-ternyata-dipicu-spg-digoda-spb-pameran | F151: bekasi.inews.id | G151: Viral Keributan di Mal Bekasi Utara, Ternyata Dipicu SPG Digoda SPB Pameran - iNews.ID | H151: iNews.ID | I151: 2026-09-08 | J151: Scan this QR or download app from: BEKASI , iNewsBekasi.id - Sebuah video di media sosial mendadak viral usai memperlihatkan keributan sengit di kawasan mal wilayah Bekasi Utara , Jawa Barat, pada Se | K151: Ragu | L151: 0.4 | M151: 0.4
A152: 150 | B152: 006 | C152: 1 | D152: 1 | E152: https://www.antarafoto.com/id/view/2852899/pameran-kuliner-jakarta-viral-di-padang | F152: www.antarafoto.com | G152: Pameran kuliner Jakarta Viral di Padang - antarafoto.com | H152: antarafoto.com | I152: 2026-08-29 | J152: Pengunjung melakukan transaksi digital membeli makanan saat digelarnya Festival Kuliner Gang Senggol Jakarta Viral di Padang, Sumatera Barat, Sabtu (29/8/2026). Pameran yang menampilkan 400 menu kulin | K152: Sesuai | L152: 1 | M152: 0.8
A153: 151 | B153: 006 | C153: 1 | D153: 0 | E153: https://www.rctiplus.com/news/detail/otomotif/5424370/viral-di-eropa--hyundai-bakal-boyong-ioniq-3-ke-giias-2026 | F153: www.rctiplus.com | G153: Viral di Eropa, Hyundai Bakal Boyong Ioniq 3 ke GIIAS 2026 - RCTI+ | H153: RCTI+ | I153: 2026-07-09 | J153: IDXChannel - Chief Operating Officer (COO) PT Hyundai Motors Indonesia (HMID), Fransiscus Soerjopranoto, membeberkan rencana memamerkan Hyundai Ioniq 3 di ajang GAIKINDO Indonesia International Auto S | K153: Sesuai | L153: 0.67 | M153: 0.71
... A231: 229 | B231: 008 | C231: 0 | D231: 0 | E231: https://www.kompasiana.com/aiesecinusu/6a69a0da34777c0d5452a5b2/tren-gen-z-berani-memulai-bisnis-sejak-dini-saatnya-asah-mentality-dan-strategi-bisnis-nyata | F231: www.kompasiana.com | G231: Tren Gen Z Berani Memulai Bisnis Sejak Dini : Saatnya Asah Mentality dan Strategi Bisnis Nyata - Kompasiana.com | H231: Kompasiana.com | I231: 2026-07-29 | J231: AIESEC in Universitas Sumatera Utara (AIESEC in USU) is part of the global AIESEC network that focuses on developing youth leadership. First established in 2013 and reactivated in 2019, AIESEC in USU | K231: Sesuai | L231: 0.67 | M231: 0.57
A232: 230 | B232: 008 | C232: 3 | D232: 0 | E232: https://www.tripzilla.id/oleh-oleh-khas-bogor/27427 | F232: www.tripzilla.id | G232: Main ke Bogor? Cek List Oleh Oleh Khas Bogor yang Paling Dicari Ini! - tripzilla.id | H232: tripzilla.id | I232: 2026-07-31 | J232: Siapa yang tidak rindu dengan udara sejuk dan kemacetan syahdu Kota Bogor? Selain wisatanya yang ciamik, Kota Hujan ini adalah surganya kuliner. Membawa pulang oleh oleh khas Bogor bukan sekadar tradi | K232: Tidak sesuai | L232: 0.29
A233: 231 | B233: 008 | C233: 3 | D233: 3 | E233: https://travel.tribunnews.com/kuliner/142986/5-cheesecake-viral-di-jakarta-pusat-cocok-untuk-oleh-oleh | F233: travel.tribunnews.com | G233: 5 Cheesecake Viral di Jakarta Pusat, Cocok untuk Oleh-oleh - Tribun Travel | H233: Tribun Travel | I233: 2026-04-29 | J233: TRIBUNTRAVEL.COM - Menikmati cheesecake di Jakarta Pusat bukan hanya tentang rasa, tetapi juga menghadirkan pengalaman kuliner yang memanjakan lidah. Jakarta Pusat menawarkan banyak pilihan dessert sh | K233: Sesuai | L233: 1 | M233: 1
A234: 232 | B234: 008 | C234: 0 | D234: 0 | E234: https://sport.detik.com/sepakbola/gila-bola/d-8605238/lagi-lagi-viral-messi-belanja-tanpa-pengawalan-seperti-warga-biasa | F234: sport.detik.com | G234: Lagi-lagi Viral Messi Belanja, Tanpa Pengawalan Seperti Warga Biasa - detiksport | H234: detiksport | I234: 2026-08-05 | J234: Lagi-lagi Viral Messi Belanja, Tanpa Pengawalan Seperti Warga Biasa Afif Farhan - detikSepakbola Lionel Messi menikmati betul hidupnya di Miami, AS. Messi sekali lagi kedapatan di tempat belanja, tanp | K234: Sesuai | L234: 1 | M234: 0.82
A235: 233 | B235: 008 | C235: 2 | D235: 0 | E235: https://travel.tribunnews.com/shopping/142761/5-tempat-beli-oleh-oleh-di-jogja-yang-ramai-lengkap-dan-terjangkau | F235: travel.tribunnews.com | G235: 5 Tempat Beli Oleh-oleh di Jogja yang Ramai, Lengkap, dan Terjangkau - Tribun Travel | H235: Tribun Travel | I235: 2026-04-07 | J235: TRIBUNTRAVEL.COM - Liburan ke Jogja rasanya belum lengkap tanpa berburu buah tangan khas yang bisa dibawa pulang untuk keluarga maupun teman. Beragam pilihan oleh-oleh tersedia di berbagai sudut kota, | K235: Sesuai | L235: 1 | M235: 0.86
A236: 234 | B236: 008 | C236: 1 | D236: 0 | E236: https://travel.kompas.com/read/2026/06/09/170000027/wisatawan-indonesia-makin-sering-liburan-ke-hidden-gem-mana-saja-?page=all | F236: travel.kompas.com | G236: Wisatawan Indonesia Makin Sering Liburan ke "Hidden Gem", Mana Saja? - Kompas.com | H236: Kompas.com | I236: 2026-06-09 | J236: Wisatawan Indonesia Makin Sering Liburan ke "Hidden Gem", Mana Saja? KOMPAS.com - Tren perjalanan wisata di Indonesia terus mengalami perubahan. Jika sebelumnya kota-kota besar dan destinasi populer m | K236: Sesuai | L236: 1 | M236: 1
A237: 235 | B237: 008 | C237: 0 | D237: 0 | E237: https://www.cnnindonesia.com/gaya-hidup/20260608171729-269-1366741/pola-wisata-di-indonesia-bergeser-turis-berbondong-buru-hidden-gems | F237: www.cnnindonesia.com | G237: Pola Wisata di Indonesia Bergeser, Turis Berbondong Buru 'Hidden Gems' - cnnindonesia.com | H237: cnnindonesia.com | I237: 2026-06-08 | J237: Pola perjalanan turis di Indonesia mengalami pergeseran signifikan. Turis kini cenderung menghindari kota-kota besar dan lebih memilih menjelajahi destinasi alternatif demi memburu keindahan alam, pen | K237: Sesuai | L237: 0.67 | M237: 0.55
A238: 236 | B238: 008 | C238: 1 | D238: 0 | E238: https://nationalgeographic.grid.id/read/134386113/destinasi-hidden-gems-indonesia-makin-diminati-wisatawan | F238: nationalgeographic.grid.id | G238: Destinasi ‘Hidden Gems’ Indonesia Makin Diminati Wisatawan - National Geographic Indonesia | H238: National Geographic Indonesia | I238: 2026-06-11 | J238: Baca berita tanpa iklan. Gabung National Geographic+ Kamis, 11 Juni 2026 | 07:38 WIB Utomo Priyambodo, Mahandis Yoanata Thamrin Mahandis Yoanata Thamrin Para wisatawan menikmati matahari tenggelam di | K238: Ragu | L238: 0.43 | M238: 0.43
A239: 237 | B239: 008 | C239: 0 | D239: 0 | E239: https://wartaekonomi.co.id/read634083/roselands-hidden-gem-rumah-tapak-di-sydney-yang-mulai-dilirik-investor-indonesia | F239: wartaekonomi.co.id | G239: Roselands, Hidden Gem Rumah Tapak di Sydney yang Mulai Dilirik Investor Indonesia - Warta Ekonomi | H239: Warta Ekonomi | I239: 2026-09-11 | J239: Keterbatasan lahan pengembangan rumah tapak di Sydney mendorong kawasan hunian baru bergeser ke wilayah suburban, terutama di bagian barat, barat daya, dan selatan kota. Perubahan ini membuka peluang | K239: Sesuai | L239: 0.9 | M239: 0.82
A240: 238 | B240: 008 | C240: 0 | D240: 0 | E240: https://www.bloombergtechnoz.com/detail-news/121027/bei-buka-gembok-saham-gocap-investor-ritel-bisa-dapat-hidden-gem | F240: www.bloombergtechnoz.com | G240: BEI Buka Gembok Saham Gocap, Investor Ritel Bisa Dapat Hidden Gem - Bloomberg Technoz | H240: Bloomberg Technoz | I240: 2026-09-09 | J240: Bloomberg Technoz, Jakarta - Rencana Bursa Efek Indonesia (BEI) menghapus batas minimum harga Rp50/saham per akhir September membuka babak baru bagi investor ritel di pasar modal Indonesia. Apa saja u | K240: Sesuai | L240: 0.6 | M240: 0.6
A241: 239 | B241: 008 | C241: 1 | D241: 0 | E241: https://harianbanyuasin.disway.id/selebriti-hiburan/read/654649/7-hidden-gem-wisata-alam-di-indonesia-yang-bikin-betah-nomor-5-dijuluki-surga-tersembunyi | F241: harianbanyuasin.disway.id | G241: 7 Hidden Gem Wisata Alam di Indonesia yang Bikin Betah! Nomor 5 Dijuluki Surga Tersembunyi - harianbanyuasin.disway.id - Harian Banyuasin | H241: Harian Banyuasin | I241: 2026-06-27 | J241: Rekomendasi destinasi wisata alam hidden gem di Indonesia--doc.istimewa HARIANBANYUASIN.COM - Di tengah padatnya pekerjaan, kemacetan, dan hiruk pikuk kehidupan sehari-hari, banyak orang mulai mencari | K241: Sesuai | L241: 0.62 | M241: 0.54
A242: 240 | B242: 009 | C242: 0 | D242: 0 | E242: https://pasardana.id/news/2026/6/10/hidden-gem-bursa-beraksi-mtdl-tebar-dividen-rp331-5-miliar-investor-dapat-rp27-per-saham | F242: pasardana.id | G242: Hidden Gem Bursa Beraksi! MTDL Tebar Dividen Rp331,5 Miliar! Investor Dapat Rp27 per Saham - pasardana.id | H242: pasardana.id | I242: 2026-06-10 | J242: 28 September 2026, 16:47 28 September 2026, 16:00 28 September 2026, 15:53 28 September 2026, 15:45 28 September 2026, 15:32 28 September 2026, 15:02 Bagi Dividen | aksi korporasi | dividen tunai | PT | K242: Sesuai | L242: 0.57 | M242: 0.57
A243: 241 | B243: 009 | C243: 0 | D243: 0 | E243: https://beritakota.id/tren-baru-liburan-ke-wisata-antimainstream-makin-diburu/ | F243: beritakota.id | G243: Target Wisata ke Kota Hidden Gem, Kampanye Visit Malaysia 2026 Gaet Commuter Line - VOI.ID | H243: VOI.ID | I243: 2026-07-29 | J243: Jakarta, Beritakota.id – Tidak semua wisatawan lagi mengejar destinasi yang ramai dikunjungi. Dalam beberapa tahun terakhir, muncul perubahan menarik pada perilaku pelancong Indonesia. Semakin banyak | K243: Tidak sesuai | L243: 0.27 | M243: 0.33
A244: 242 | B244: 009 | C244: 0 | D244: 0 | E244: https://voi.id/lifestyle/587128/target-wisata-ke-kota-hidden-gem-kampanye-visit-malaysia-2026-gaet-commuter-line | F244: voi.id | G244: Tren Wisata Indonesia 2026: Bali Raih Predikat Terbaik Dunia hingga Munculnya Fenomena Hidden Gem Baru - Harapan Rakyat | H244: Harapan Rakyat | I244: 2026-04-18 | J244: You must confirm your age to access this page. JAKARTA - Tourism Malaysia bekerja sama dengan PT. Kereta Commuter Indonesia (KAI Commuter) untuk menghadirkan kampanye Visit Malaysia 2026 secara masif. | K244: Tidak sesuai (isi = judul artikel N-1) | L244: 0.17 | M244: 0.58
... A276: 274 | B276: 010 | C276: 0 | D276: 0 | E276: https://www.kompas.tv/regional/685670/viral-cctv-petugas-diduga-ambil-rokok-saat-razia-satpol-pp-aceh-utara-membantah-sapa-malam | F276: www.kompas.tv | G276: Polisi Nekat Rampok Toko Emas di Aceh dengan Senjata Laras Panjang - The Great Mischief | H276: The Great Mischief | I276: 2026-08-16 | J276: KOMPAS.TV – Satpol PP-WH Aceh Utara membantah anggotanya mengambil rokok milik pedagang saat razia rokok ilegal. Dugaan tersebut muncul setelah rekaman CCTV yang memperlihatkan aktivitas petugas saat | K276: Tidak sesuai (isi = judul artikel N-1) | L276: 0.22 | M276: 0.69
A277: 275 | B277: 010 | C277: 0 | D277: 0 | E277: https://www.upplan.sg/news/005e099994.html | F277: www.upplan.sg | G277: Seorang oknum anggota kepolisian berinisial MZ (28) ditangkap setelah diduga melakukan aksi perampokan di sebuah toko emas di Kecamatan Tapaktuan, Kabupaten Aceh Selatan, Sabtu (18/7/2026). Pelaku diamankan sekitar 11 jam setelah kejadian. Ber - facebook.com | H277: facebook.com | I277: 2026-07-19 | J277: PMF , aliansi kelompok paramiliter yang sebelumnya berdiri sendiri dan kini terintegrasi ke dalam angkatan bersenjata, mengakhiri jeda singkat dalam pertempuran dengan melancarkan serangan terbaru. Se | K277: Tidak sesuai | L277: 0.08
A278: 276 | B278: 010 | C278: 0 | D278: 0 | E278: https://sumut.idntimes.com/news/sumatra-utara/perampok-bersenjata-laras-panjang-gasak-toko-emas-di-aceh-selatan-00-qynp2-3nzxvk | F278: sumut.idntimes.com | G278: Curhat Pelajar pada Bupati Aceh Timur, Diinjak di Wajah oleh Perempuan karena Dituduh Curi Rp 10.000 - Kompas.com | H278: Kompas.com | I278: 2026-07-10 | J278: Banda Aceh, IDN Times - Aksi perampokan bersenjata menggegerkan warga Tapaktuan, Kabupaten Aceh Selatan, Aceh, pada Sabtu (18/7/2026). Seorang pria yang diduga membawa senjata laras panjang merampok T | K278: Tidak sesuai (isi = judul artikel N-1) | L278: 0.08 | M278: 0.54
A279: 277 | B279: 010 | C279: 0 | D279: 0 | E279: https://regional.kompas.com/read/2026/07/10/222604278/curhat-pelajar-pada-bupati-aceh-timur-diinjak-di-wajah-oleh-perempuan?page=all | F279: regional.kompas.com | G279: Motif Polisi Rampok Toko Emas di Aceh Selatan: Tekanan Ekonomi - Kompas.com | H279: Kompas.com | I279: 2026-07-20 | J279: Curhat Pelajar pada Bupati Aceh Timur, Diinjak di Wajah oleh Perempuan karena Dituduh Curi Rp 10.000 IDI, KOMPAS.com - IR, pelajar SMP di Kabupaten Aceh Timur, Provinsi Aceh mengeluarkan curahan hati | K279: Tidak sesuai (isi = judul artikel N-1) | L279: 0.33 | M279: 1
A280: 278 | B280: 010 | C280: 0 | D280: 0 | E280: https://regional.kompas.com/read/2026/07/20/141508278/motif-polisi-rampok-toko-emas-di-aceh-selatan-tekanan-ekonomi | F280: regional.kompas.com | G280: 3 Orang Diperiksa Terkait Seleb Aceh Besar Pamer Kelamin saat Live TikTok - detikcom | H280: detikcom | I280: 2026-07-20 | J280: Motif Polisi Rampok Toko Emas di Aceh Selatan: Tekanan Ekonomi ACEH SELATAN, KOMPAS.com - Polda Aceh mengungkap motif sementara di balik aksi perampokan toko emas yang dilakukan seorang oknum anggota | K280: Tidak sesuai (isi = judul artikel N-1) | L280: 0.1 | M280: 1
A281: 279 | B281: 010 | C281: 0 | D281: 0 | E281: https://www.detik.com/sumut/hukum-dan-kriminal/d-8582735/3-orang-diperiksa-terkait-seleb-aceh-besar-pamer-kelamin-saat-live-tiktok | F281: www.detik.com | G281: Pria Spesialis Pencuri Beras di Banda Aceh Ditangkap Polisi - detikcom | H281: detikcom | I281: 2026-08-10 | J281: Penyidik polisi syariah (Wilayatul Hisbah/WH) memeriksa dua perempuan dan satu pria terkait kasus pemilik akun TikTok 'Selep Aceh Besar' memamerkan kelamin saat siaran langsung (live). Belum ada yang | K281: Tidak sesuai (isi = judul artikel N-1) | L281: 0.38 | M281: 0.62
A282: 280 | B282: 010 | C282: 0 | D282: 0 | E282: https://www.detik.com/sumut/hukum-dan-kriminal/d-8611610/pria-spesialis-pencuri-beras-di-banda-aceh-ditangkap-polisi | F282: www.detik.com | G282: ANAT Fair 2026 Digelar, Banda Aceh Bidik Wisatawan Tinggal Lebih Lama dan Belanja Produk Lokal - distori.id | H282: distori.id | I282: 2026-09-25 | J282: Seorang pria asal Aceh Barat, RWN (34) ditangkap polisi karena diduga mencuri tujuh karung beras di toko UD Zaffira Gampong Lamdom, Banda Aceh. Aksinya terekam kamera CCTV dan viral di media sosial. " | K282: Tidak sesuai (isi = judul artikel N-1) | L282: 0.17 | M282: 0.55
A283: 281 | B283: 010 | C283: 1 | D283: 0 | E283: https://distori.id/2026/09/26/anat-fair-2026-digelar-banda-aceh-bidik-wisatawan-tinggal-lebih-lama-dan-belanja-produk-lokal/ | F283: distori.id | G283: Jelang Idul Adha: Warga Banda Aceh Serbu Toko Kue Kering - Waspada Aceh | H283: Waspada Aceh | I283: 2026-05-25 | J283: DISTORI.ID - Sekretaris Daerah Kota Banda Aceh Jalaluddin secara resmi membuka ASTINDO Nanggroe Aceh Travel Fair (ANAT Fair) 2026 di Suzuya Mall Banda Aceh, Jumat (25/9/2026). Mengusung tema “Jelajahi | K283: Tidak sesuai (isi = judul artikel N-1) | L283: 0.3 | M283: 0.58
A284: 282 | B284: 010 | C284: 0 | D284: 0 | E284: https://waspadaaceh.com/jelang-idul-adha-warga-banda-aceh-serbu-toko-kue-kering/ | F284: waspadaaceh.com | G284: Temuan BPK: Penatausahaan Belanja Jamuan Tamu Rp549,4 Juta di Sekretariat Daerah Tak Tertib - AJNN.net | H284: AJNN.net | I284: 2026-07-02 | J284: Banda Aceh (Waspada Aceh) – Ratusan warga terlihat menyerbu toko kue kering di berbagai tempat di Kota Banda Aceh, jelang Idul Adha 2026, untuk mengisi toples-toples di rumahnya. Tradisi ini terjadi d | K284: Tidak sesuai (isi = judul artikel N-1) | L284: 0.18 | M284: 0.9
A285: 283 | B285: 010 | C285: 0 | D285: 0 | E285: https://www.ajnn.net/news/temuan-bpk-penatausahaan-belanja-jamuan-tamu-rp549-4-juta-di-sekretariat-daerah-tak-terbib/index.html | F285: www.ajnn.net | G285: BPK Ungkap Belanja Ratusan Juta Tanpa Bukti Pertanggungjawaban di Tiga SKPK Pemko Subulussalam - AJNN.net | H285: AJNN.net | I285: 2026-07-28 | J285: LHOKSEUMAWE - Badan Pemeriksa Keuangan (BPK) Perwakilan Aceh menemukan pengadaan dan penatausahaan bukti pertanggungjawaban realisasi belanja makanan dan minuman jamuan jamu pada Sekretariat Daerah Ko | K285: Tidak sesuai (isi = judul artikel N-1) | L285: 0.33 | M285: 0.75
A286: 284 | B286: 010 | C286: 0 | D286: 0 | E286: https://www.ajnn.net/news/bpk-ungkap-belanja-ratusan-juta-tanpa-bukti-pertanggungjawaban-di-tiga-skpk-pemko-subulussalam/index.html | F286: www.ajnn.net | G286: Pasar Tani Aceh di Bireuen Raup Rp68,8 Juta, Harga Cabai dan Bawang Lebih Murah - POSKOTASUMATERA.COM | H286: POSKOTASUMATERA.COM | I286: 2026-09-24 | J286: SUBULUSSALAM – Badan Pemeriksa Keuangan (BPK) menemukan pembayaran Belanja Barang dan Jasa pada tiga Satuan Kerja Perangkat Kota (SKPK) Pemerintah Kota Subulussalam tidak sesuai ketentuan dengan nilai | K286: Tidak sesuai (isi = judul artikel N-1) | L286: 0 | M286: 0.69
A287: 285 | B287: 010 | C287: 0 | D287: 0 | E287: https://www.poskotasumatera.com/2026/09/pasar-tani-aceh-di-bireuen-raup-rp688.html | F287: www.poskotasumatera.com | G287: Keumamah Aceh Tembus Pasar Malaysia hingga Eropa - RRI.co.id | H287: RRI.co.id | I287: 2026-09-18 | J287: POSKOTASUMATRA.COM | BIREUEN– Upaya menekan harga pangan sekaligus membuka akses pasar langsung bagi petani kembali digencarkan Pemerintah Aceh. Melalui Pasar Tani Aceh Road Show 2026, masyarakat Bire | K287: Tidak sesuai (isi = judul artikel N-1) | L287: 0.33 | M287: 0.67
A288: 286 | B288: 010 | C288: 0 | D288: 0 | E288: https://rri.co.id/lhokseumawe/ekonomi/umkm/2739290/keumamah-aceh-tembus-pasar-malaysia-hingga-eropa | F288: rri.co.id | G288: Dari Produk Lokal ke Pasar Lebih Luas, UMKM Aceh Tumbuh Bersama Rumah BUMN Pertamina - indodaily.co | H288: indodaily.co | I288: 2026-09-17 | J288: RRI.CO.ID, Banda Aceh – Keumamah, makanan khas Aceh berbahan dasar ikan, kini tidak hanya dikenal di pasar lokal. Produk olahan tersebut telah dipasarkan hingga Malaysia, Selandia Baru, dan sejumlah n | K288: Tidak sesuai (isi = judul artikel N-1) | L288: 0.45 | M288: 0.67
A289: 287 | B289: 010 | C289: 0 | D289: 0 | E289: https://indodaily.co/dari-produk-lokal-ke-pasar-lebih-luas-umkm-aceh-tumbuh-bersama-rumah-bumn-pertamina/ | F289: indodaily.co | G289: Petani Dapat Akses Pasar, Warga Serbu Harga Murah: Road Show Pasar Tani Aceh 2026 Digelar di Aceh Barat - POSKOTASUMATERA.COM | H289: POSKOTASUMATERA.COM | I289: 2026-09-23 | J289: JAKARTA, INDODAILY.CO. – Pertamina terus memperkuat pemberdayaan ekonomi masyarakat di Aceh melalui Rumah BUMN Pertamina Aceh Tamiang dan Aceh Timur. Kehadiran Rumah BUMN menjadi wadah pembinaan bagi | K289: Tidak sesuai (isi = judul artikel N-1) | L289: 0.21 | M289: 0.82
... A653: 651 | B653: 022 | C653: 2 | D653: 2 | E653: https://travel.tribunnews.com/kuliner/143435/5-mie-ayam-viral-di-solo-jawa-tengah-yang-wajib-dicoba-mulai-rp-8000 | F653: travel.tribunnews.com | G653: 13 Restoran di Magelang Yang Memanjakan Lidah Dan Punya Pemandangan Cantik - tripzilla.id | H653: tripzilla.id | I653: 2026-06-06 | J653: TRIBUNTRAVEL.COM - Serunya kulineran di Solo memang nggak pernah gagal bikin siapa pun jatuh hati dengan cita rasanya yang khas. Salah satu menu favorit yang selalu dicari adalah mie ayam dengan berba | K653: Tidak sesuai (isi = judul artikel N-1) | L653: 0.29 | M653: 1
A654: 652 | B654: 022 | C654: 3 | D654: 0 | E654: https://www.tripzilla.id/restoran-di-magelang/27185 | F654: www.tripzilla.id | G654: 14 Rekomendasi Makanan di Solo yang Murah dan Enak, Kuliner Khas Wajib Dicoba! - detikcom | H654: detikcom | I654: 2026-05-02 | J654: Magelang selama ini mungkin lebih sering dikenal karena kemegahan Candi Borobudur atau keindahan panorama alamnya yang dikelilingi pegunungan. Namun, tahukah kamu kalau kota sejuk ini juga menyimpan s | K654: Tidak sesuai (isi = judul artikel N-1) | L654: 0.33
A655: 653 | B655: 022 | C655: 2 | D655: 0 | E655: https://www.detik.com/jateng/kuliner/d-8471054/14-rekomendasi-makanan-di-solo-yang-murah-dan-enak-kuliner-khas-wajib-dicoba | F655: www.detik.com | G655: 5 Warung Makan Hits di Jakarta, Ada Spesialis Sambal hingga Nasi Bali Halal - detikFood | H655: detikFood | I655: 2026-05-21 | J655: Solo emang surganya buat detikers yang hobi jajan tapi nggak mau kantong jebol. Ada banyak banget pilihan makanan di Solo yang murah dan enak yang bisa dicari di tiap sudut kota. Rasanya juga otentik | K655: Tidak sesuai (isi = judul artikel N-1) | L655: 0.22 | M655: 0.9
A656: 654 | B656: 022 | C656: 2 | D656: 0 | E656: https://food.detik.com/warung-makan/d-8497945/5-warung-makan-hits-di-jakarta-ada-spesialis-sambal-hingga-nasi-bali-halal | F656: food.detik.com | G656: 8 Kuliner dan Tempat Makan di Pasar Johar Semarang Yang Bikin Kenyang dan Segar - tripzilla.id | H656: tripzilla.id | I656: 2026-05-18 | J656: Memasuki tanggal tua, kulineran di warung makan bisa jadi pilihan hemat. Meski konsepnya warung, pilihan makanan di lima tempat makan ini beragam dan pastinya punya harga terjangkau! Jakarta punya ban | K656: Tidak sesuai (isi = judul artikel N-1) | L656: 0.33 | M656: 0.78
A657: 655 | B657: 022 | C657: 3 | D657: 0 | E657: https://www.tripzilla.id/kuliner-pasar-johar-semarang/27048 | F657: www.tripzilla.id | G657: 6 Tempat Makan 'Ndeso' di Tangerang buat Long Weekend Bareng Keluarga - detikFood | H657: detikFood | I657: 2026-05-14 | J657: Trend wisata kuliner di pasar kini juga terjadi di Semarang. Salah satu pasar tradisional paling populer di Semarang adalah Pasar Johar yang juga punya banyak kuliner tradisional menarik yang semakin | K657: Tidak sesuai (isi = judul artikel N-1) | L657: 0.25 | M657: 1
A658: 656 | B658: 022 | C658: 2 | D658: 1 | E658: https://food.detik.com/tempat-makan/d-8487993/6-tempat-makan-ndeso-di-tangerang-buat-long-weekend-bareng-keluarga | F658: food.detik.com | G658: 10 Kafe di Magelang Dari Instagramable Hingga Punya View Alam - tripzilla.id | H658: tripzilla.id | I658: 2026-05-22 | J658: Liburan long weekend kali ini bisa menikmati kuliner 'ndeso' di sekitar Tangerang. Mulai dari masakan Jawa sampai menu Betawi ada di sini! Di tengah menjamurnya restoran modern dan kafe kekinian, waru | K658: Tidak sesuai (isi = judul artikel N-1) | L658: 0.33 | M658: 1
A659: 657 | B659: 022 | C659: 3 | D659: 0 | E659: https://www.tripzilla.id/kafe-di-magelang/27079 | F659: www.tripzilla.id | G659: 14 Tempat Makan Babi di Solo dan Sukoharjo: Rasanya Khas, Juicy, dan Nendang! - detikcom | H659: detikcom | I659: 2026-04-22 | J659: Lebih dari sekadar rumah bagi Candi Borobudur, Magelang kini tumbuh menjadi magnet baru bagi para pecinta kuliner dan tempat estetik. Kota sejuk ini seolah tak pernah kehabisan ide untuk memanjakan pe | K659: Tidak sesuai (isi = judul artikel N-1) | L659: 0.22
A660: 658 | B660: 022 | C660: 0 | D660: 0 | E660: https://www.detik.com/jateng/kuliner/d-8455677/14-tempat-makan-babi-di-solo-dan-sukoharjo-rasanya-khas-juicy-dan-nendang | F660: www.detik.com | G660: Sederet Fakta soal Warung Babi yang Ditolak Warga di Sukoharjo - detikcom | H660: detikcom | I660: 2026-04-18 | J660: Solo memang dikenal sebagai surga kuliner yang tak pernah tidur. Bagi kamu yang mencari variasi hidangan non-halal, kota ini menyimpan banyak permata tersembunyi yang menggugah selera. Akan dirangkum | K660: Sesuai | L660: 0.57 | M660: 0.55
A661: 659 | B661: 022 | C661: 1 | D661: 1 | E661: https://www.detik.com/jateng/berita/d-8449575/sederet-fakta-soal-warung-babi-yang-ditolak-warga-di-sukoharjo | F661: www.detik.com | G661: 7 Tempat Wisata Pegunungan Sejuk di Jawa Tengah Selain Dieng - detikTravel | H661: detikTravel | I661: 2026-07-12 | J661: Sebuah video yang menunjukkan akses jalan menuju warung makan di Sukoharjo viral di media sosial. Jalan yang mengarah ke tempat makan bernama Mie dan Babi Tepi Sawah itu tertutup dengan tumpukan tanah | K661: Ragu | L661: 0.38 | M661: 0.5
A662: 660 | B662: 023 | C662: 2 | D662: 0 | E662: https://travel.detik.com/domestic-destination/d-8570078/7-tempat-wisata-pegunungan-sejuk-di-jawa-tengah-selain-dieng | F662: travel.detik.com | G662: Jateng Targetkan 1.000 Desa Wisata Baru, Daerah Ini Diminta Bersiap - Bisnis.com - Semarang | H662: Bisnis.com - Semarang | I662: 2026-06-23 | J662: Bosan dengan Dieng tapi tetap butuh pelarian ke tempat yang dingin dan bikin adem pikiran? Tenang, Jawa Tengah punya banyak stok destinasi dataran tinggi yang hawanya mirip kulkas. Jawa Tengah menyimp | K662: Tidak sesuai (isi = judul artikel N-1) | L662: 0.11 | M662: 0.6
A663: 661 | B663: 023 | C663: 1 | D663: 1 | E663: https://travel.kompas.com/read/2026/04/19/171531127/wisata-viral-di-kebumen-pemandangan-laut-lepas-dari-ketinggian-bikin-betah | F663: travel.kompas.com | G663: Wisata Negeri Kahyangan Magelang 2026, Destinasi Viral di Lereng Merbabu Paling Menakjubkan - jogja.disway.id - Disway Jogja | H663: Disway Jogja | I663: 2026-05-11 | J663: Wisata Viral di Kebumen, Pemandangan Laut Lepas dari Ketinggian Bikin Betah KEBUMEN, KOMPAS.com – Momen libur selalu identik dengan kegiatan wisata bersama keluarga. Sejumlah tempat wisata alam pun ba | K663: Tidak sesuai | L663: 0.18 | M663: 1
A664: 662 | B664: 023 | C664: 1 | D664: 1 | E664: https://jogja.disway.id/wisata/read/699063/wisata-negeri-kahyangan-magelang-2026-destinasi-viral-di-lereng-merbabu-paling-menakjubkan | F664: jogja.disway.id | G664: Harga Tiket Masuk Solo Safari, Tempat Ketemu Orang Utan Didi yang Viral - Tribun Travel | H664: Tribun Travel | I664: 2026-08-19 | J664: Wisata Negeri Kahyangan Magelang-- diswayjogja.id - Kabupaten Magelang memang tidak pernah berhenti memberikan kejutan bagi para pecinta perjalanan alam. Di tengah kepopuleran Candi Borobudur, terseli | K664: Tidak sesuai (isi = judul artikel N-1) | L664: 0.3 | M664: 0.78
A665: 663 | B665: 023 | C665: 1 | D665: 1 | E665: https://travel.tribunnews.com/destinasi/144389/harga-tiket-masuk-solo-safari-tempat-ketemu-orang-utan-didi-yang-viral | F665: travel.tribunnews.com | G665: Viral Video Pendakian Warga Saat Gunung Merapi Status Siaga, Bagaimana Duduk Perkaranya? - Kompas.id | H665: Kompas.id | I665: 2026-07-03 | J665: TRIBUNTRAVEL.COM - Liburan ke Solo semakin seru dengan hadirnya destinasi wisata keluarga yang menawarkan pengalaman berbeda. Kota ini kini tidak hanya dikenal dengan budaya, tetapi juga memiliki temp | K665: Tidak sesuai (isi = judul artikel N-1) | L665: 0 | M665: 0.91
A666: 664 | B666: 023 | C666: 1 | D666: 1 | E666: https://www.kompas.id/artikel/viral-video-pendakian-warga-saat-gunung-merapi-masih-siaga-bagiamana-duduk-perkaranya | F666: www.kompas.id | G666: Perahu Tradisional Hingga Wisata Dadakan di Sungai Serayu yang Surut - rmol jateng | H666: rmol jateng | I666: 2026-07-26 | J666: Di media sosial viral video terkait pendakian sejumlah warga ke Gunung Merapi via Selo, Boyolali, saat kondisi gunung masih Siaga. Bagaimana duduk perkaranya? 03 Jul 2026 07:30 WIB · Nasional Kompas/F | K666: Tidak sesuai (isi = judul artikel N-1) | L666: 0 | M666: 0.89
A667: 665 | B667: 023 | C667: 1 | D667: 1 | E667: https://www.rmoljawatengah.id/dari-perahu-tradisional-hingga-wisata-dadakan-sungai-serayu | F667: www.rmoljawatengah.id | G667: Kopdes Merah Putih “di Atas Awan” Lereng Gunung Prau, Warganet Soroti Potensi Wisata Desa - Sumut Pos | H667: Sumut Pos | I667: 2026-07-08 | J667: Surutnya Sungai Serayu di Desa Srowot lewat kearifan lokal dengan pemanfaatan media sosial, dan jiwa adaptif warga, keterbatasan alam justru berhasil disulap menjadi peluang ekonomi kreatif dan desti | K667: Tidak sesuai (isi = judul artikel N-1) | L667: 0.15 | M667: 0.83
A668: 666 | B668: 023 | C668: 1 | D668: 1 | E668: https://travel.tribunnews.com/destinasi/143669/harga-tiket-masuk-pony-park-wisata-terbaru-di-klaten-untuk-libur-sekolah | F668: travel.tribunnews.com | G668: Sungai Serayu Banyumas Surut, Wisata Perahu Dadakan Panen Cuan - detikcom | H668: detikcom | I668: 2026-07-22 | J668: TRIBUNTRAVEL.COM - Lagi liburan ke Klaten , ada tempat wisata baru yang menarik banget untuk dikunjungi. Destinasi ramah anak ini cocok banget dikunjungi saat libur sekolah 2026 bersama keluarga terci | K668: Tidak sesuai | L668: 0.11 | M668: 0.91
A669: 667 | B669: 023 | C669: 1 | D669: 1 | E669: https://www.detik.com/jateng/wisata/d-8585907/sungai-serayu-banyumas-surut-wisata-perahu-dadakan-panen-cuan | F669: www.detik.com | G669: Viral Juru Parkir Kepruk Tarif Rp 10 Ribu di Tahir Solo Museum - detikcom | H669: detikcom | I669: 2026-08-14 | J669: Surutnya aliran Sungai Serayu akibat kemarau panjang jadi berkah bagi sebagian warga Desa Srowot, Kecamatan Kalibagor, Banyumas. Di kawasan yang kini dikenal dengan nama Wadas Cinta Carik, warga membu | K669: Tidak sesuai (isi = judul artikel N-1) | L669: 0 | M669: 0.7
A670: 668 | B670: 023 | C670: 1 | D670: 1 | E670: https://www.detik.com/jateng/berita/d-8618566/viral-juru-parkir-kepruk-tarif-rp-10-ribu-di-tahir-solo-museum | F670: www.detik.com | G670: 11 Objek Wisata di Solo untuk Liburan Seru, Yuk Kunjungi! - Pegadaian | H670: Pegadaian | I670: 2026-08-05 | J670: Viral soal tarif parkir ngepruk kembali terjadi di Kota Solo. Kali ini laporan datang dari pengunjung Tahir Museum Solo yang mengaku dikepruk Rp 10 ribu. Keluhan pengunjung itu diunggah akun Instagram | K670: Tidak sesuai (isi = judul artikel N-1) | L670: 0.14 | M670: 0.78
A671: 669 | B671: 023 | C671: 2 | D671: 0 | E671: https://pegadaian.co.id/artikel/inspirasi/wisata-di-solo | F671: pegadaian.co.id | G671: 5 Tempat Beli Oleh-oleh Lengkap di Semarang, Moaci hingga Lunpia - Tribun Travel | H671: Tribun Travel | I671: 2026-04-14 | J671: Oleh Pegadaian dalam Inspirasi Libur panjang sebentar lagi tiba! Jika mencari tempat wisata di Solo yang seru dan tidak membosankan, kota di Jawa Tengah ini adalah pilihan liburan yang sangat tepat. W | K671: Tidak sesuai (isi = judul artikel N-1) | L671: 0.33 | M671: 1
... A908: 906 | B908: 031 | C908: 0 | D908: 0 | E908: https://www.owrite.id/hype/2026/07/07/viral-video-tim-agrinas-sebut-kopdes-bisa-hasilkan-omzet-rp400-juta-per-bulan-netizen-auto-nyinyir/ | F908: www.owrite.id | G908: Polisi Selidiki Dugaan Pelecehan di ST Kebayoran Lama, Pemulihan Aceh Capai 95% | Menyapa Indonesia - SinPo.id | H908: SinPo.id | I908: 2026-05-06 | J908: 7 Juli 2026 · 19.27 WIB 7 Jul 2026 · 19.27 WIB Beredar sebuah video seorang pria yang diduga tim Agrinas tengah memberikan pendampingan kepada pengurus Koperasi Desa Merah Putih (Kopdes) di Nusa Tengg | K908: Tidak sesuai | L908: 0 | M908: 0.64
A909: 907 | B909: 031 | C909: 0 | D909: 0 | E909: https://lingkar.co/berita/pengamat20isu20beli20bbm20subsidi20wajib20lunas20pajak20kendaraan20kebijaka | F909: lingkar.co | G909: Cut Salwa, TikToker Asal Aceh Mendadak Viral, Videonya Bikin Warganet Penasaran - Habadaily | H909: Habadaily | I909: 2026-06-05 | J909: Lingkar.co - Isu pembelian BBM bersubsidi harus dibarengi dengan status pajak kendaraan bermotor yang lunas kembali ramai diperbincangkan. Video pengumuman… Lingkar .co Isu pembelian BBM bersubsidi ha | K909: Tidak sesuai | L909: 0
A910: 908 | B910: 031 | C910: 0 | D910: 0 | E910: https://www.bbc.com/indonesia/articles/ce85mmz83qjo | F910: www.bbc.com | G910: Festival Kuliner Serpong 2026, Menjelajah Nikmatnya Sambal Seruit Lampung hingga Mie Aceh Seulawah - investor.id | H910: investor.id | I910: 2026-09-13 | J910: Sumber gambar, ANTARA FOTO/Johanes Viandinando Jumlah korban tewas akibat gempa di Pulau Flores, Nusa Tenggara Timur (NTT), bertambah menjadi 103 orang per Selasa (25/08) sore, menurut data Badan Nasi | K910: Tidak sesuai | L910: 0 | M910: 0
A911: 909 | B911: 031 | C911: 0 | D911: 0 | E911: https://wartaekonomi.co.id/read628940/pemprov-ntt-tetapkan-status-tanggap-darurat-gempa-bumi-selama-14-hari | F911: wartaekonomi.co.id | G911: Illiza akan Sulap Terminal Keudah jadi Lokasi Event Kota - Seputar Aceh | H911: Seputar Aceh | I911: 2026-07-22 | J911: Pemerintah Provinsi Nusa Tenggara Timur (Pemprov NTT) menetapkan Status Tanggap Darurat Bencana Gempa Bumi di Provinsi NTT selama 14 hari, terhitung mulai 15 hingga 28 Agustus 2026. Penetapan tersebut | K911: Tidak sesuai | L911: 0.14 | M911: 0.82
A912: 910 | B912: 031 | C912: 1 | D912: 0 | E912: https://kupang.antaranews.com/berita/193357/ditjenpas-ntt-mendorong-produk-unggulan-warga-binaan-masuk-pasar-umkm | F912: kupang.antaranews.com | G912: Ada Festival Lhok Buloh di Aceh Utara, Bisa Nonton Tari dan Kulineran - Kompas.com | H912: Kompas.com | I912: 2026-06-13 | J912: Kupang, NTT (ANTARA) - Kantor Wilayah Direktorat Jenderal Pemasyarakatan Nusa Tenggara Timur (Ditjenpas NTT) mendorong produk unggulan warga binaan masuk pasar UMKM melalui Bazar Hari Bhayangkara ke-8 | K912: Tidak sesuai | L912: 0 | M912: 1
A913: 911 | B913: 031 | C913: 0 | D913: 0 | E913: https://www.detik.com/bali/berita/d-8493459/pedagang-tewas-mendadak-di-pasar-kupang-diduga-serangan-jantung | F913: www.detik.com | G913: Stan UTU Tampilkan Karya dan Dorong Minat Baca di Festival Literasi Aceh Barat - RRI.co.id | H913: RRI.co.id | I913: 2026-09-25 | J913: Pedagang Tewas Mendadak di Pasar Kupang Diduga Serangan Jantung Yufengki Bria - detikBali Polisi mengungkap penyebab kematian pria bernama Mesak Oemanu (56) di Pasar Oefitis, Desa Oelfatu, Kecamatan A | K913: Tidak sesuai | L913: 0.09 | M913: 0.89
A914: 912 | B914: 031 | C914: 0 | D914: 0 | E914: https://www.merahputih.com/post/read/pasar-ruteng-ntt-rusak-mendag-datangkan-bahan-pokok-dari-jatim-dan-ntb | F914: www.merahputih.com | G914: Dukung Festival Sagu Singkel 2026, PT Nafasindo Tegaskan Komitmen Jaga Warisan Budaya - ketik.com | H914: ketik.com | I914: 2026-07-22 | J914: MERAHPUTIH.COM - MENTERI Perdagangan (Mendag) Budi Santoso menegaskan terdapat kerusakan satu pasar akibat gempa bumi NTT. Pasar tersebut yakni Pasar Inpres Ruteng NTT. Pemerintah telah meminta agar p | K914: Tidak sesuai | L914: 0 | M914: 0.7
A915: 913 | B915: 031 | C915: 0 | D915: 0 | E915: https://news.detik.com/berita/d-8624121/mendag-serahkan-bantuan-rp-250-juta-untuk-korban-gempa-ntt | F915: news.detik.com | G915: Wajib Disinggahi, 6 Tempat Makan Seafood Enak di Sibolga - IDN Times Sumut | H915: IDN Times Sumut | I915: 2026-04-11 | J915: Menteri Perdagangan Budi Santoso (Busan) menyerahkan bantuan 'Kemendag Peduli' senilai Rp250 juta untuk masyarakat terdampak gempa bumi di Nusa Tenggara Timur (NTT). Bantuan diserahkan secara simbolis | K915: Tidak sesuai | L915: 0 | M915: 0.71
A916: 914 | B916: 031 | C916: 0 | D916: 0 | E916: https://www.detik.com/bali/nusra/d-8495433/viral-warga-estafet-gotong-peti-jenazah-gegara-jembatan-putus-di-amfoang-ntt | F916: www.detik.com | G916: 8 Rekomendasi Rumah Makan Padang di Jakarta, Kuliner Autentik Minang - Kompas.com | H916: Kompas.com | I916: 2026-05-19 | J916: Viral Warga Estafet Gotong Peti Jenazah gegara Jembatan Putus di Amfoang NTT Yufengki Bria - detikBali Sejumlah warga menggotong peti jenazah secara estafet melewati sungai lantaran jembatan di Desa M | K916: Tidak sesuai | L916: 0 | M916: 0.83
A917: 915 | B917: 031 | C917: 0 | D917: 0 | E917: https://www.detik.com/bali/nusra/d-8529267/gelar-demo-aliansi-ntt-menggugat-kritik-program-mbg-hingga-kopdes-merah-putih | F917: www.detik.com | G917: Tragis! Truk Ugal-ugalan Hantam Rumah Makan di Tapteng - RRI.co.id | H917: RRI.co.id | I917: 2026-06-01 | J917: Gelar Demo, Aliansi NTT Menggugat Kritik Program MBG hingga Kopdes Merah Putih Simon Selly - detikBali Aliansi NTT Menggugat menggelar aksi demonstrasi di Kota Kupang, Nusa Tenggara Timur (NTT), siang | K917: Tidak sesuai | L917: 0.12 | M917: 0.85
A918: 916 | B918: 031 | C918: 0 | D918: 0 | E918: https://www.kompas.id/artikel/sekolah-dihancurkan-demi-koperasi-merah-putih-pdip-angkat-bicara | F918: www.kompas.id | G918: 7 Rekomendasi BPK Paling Populer di Medan, Kuliner Non-Halal Wajib Dicoba - detikcom | H918: detikcom | I918: 2026-05-13 | J918: Penghancuran sebagian bangunan SDN Wolomoni demi proyek Koperasi Desa Merah Putih memicu kecaman DPR, warga, dan tokoh adat. 08 Jun 2026 19:50 WIB · Politik & Hukum Oleh Frans Pati Herin KUPANG, KOMPA | K918: Tidak sesuai | L918: 0 | M918: 0.89
A919: 917 | B919: 031 | C919: 1 | D919: 0 | E919: https://www.kompas.tv/regional/661239/momen-wapres-gibran-resmi-buka-festival-paskah-2026-di-kupang-jmp | F919: www.kompas.tv | G919: 5 Tempat Wajib Kamu Coba untuk Makan Sushi Enak di Medan - IDN Times Sumut | H919: IDN Times Sumut | I919: 2026-06-28 | J919: KUPANG, KOMPAS.TV - Wapres Gibran Rakabuming Raka membuka Festival Paskah yang digelar di Kota Kupang, Nusa Tenggara Timur. Wapres Gibran mengapresiasi gelaran festival ini membawa pesan damai dan tol | K919: Tidak sesuai | L919: 0.12 | M919: 0.6
...

Sheet Per Provinsi
A1: Provinsi | B1: Jumlah tempat | C1: Viral eksplisit | D1: Kafe | E1: Restoran | F1: Wisata Alam | G1: Museum | H1: Wahana | I1: Pameran | J1: lainnya
A2: Aceh | B2: =COUNTIF(Tempat!$I$2:$I$1789,A2) -> 30 | C2: =COUNTIFS(Tempat!$I$2:$I$1789,A2,Tempat!$Q$2:$Q$1789,"Ya") -> 8 | D2: =COUNTIFS(Tempat!$I$2:$I$1789,$A2,Tempat!$D$2:$D$1789,D$1) -> 0 | E2: =COUNTIFS(Tempat!$I$2:$I$1789,$A2,Tempat!$D$2:$D$1789,E$1) -> 0 | F2: =COUNTIFS(Tempat!$I$2:$I$1789,$A2,Tempat!$D$2:$D$1789,F$1) -> 19 | G2: =COUNTIFS(Tempat!$I$2:$I$1789,$A2,Tempat!$D$2:$D$1789,G$1) -> 2 | H2: =COUNTIFS(Tempat!$I$2:$I$1789,$A2,Tempat!$D$2:$D$1789,H$1) -> 1 | I2: =COUNTIFS(Tempat!$I$2:$I$1789,$A2,Tempat!$D$2:$D$1789,I$1) -> 7 | J2: =COUNTIFS(Tempat!$I$2:$I$1789,$A2,Tempat!$D$2:$D$1789,J$1) -> 1
A3: Bali | B3: =COUNTIF(Tempat!$I$2:$I$1789,A3) -> 56 | C3: =COUNTIFS(Tempat!$I$2:$I$1789,A3,Tempat!$Q$2:$Q$1789,"Ya") -> 13 | D3: =COUNTIFS(Tempat!$I$2:$I$1789,$A3,Tempat!$D$2:$D$1789,D$1) -> 4 | E3: =COUNTIFS(Tempat!$I$2:$I$1789,$A3,Tempat!$D$2:$D$1789,E$1) -> 25 | F3: =COUNTIFS(Tempat!$I$2:$I$1789,$A3,Tempat!$D$2:$D$1789,F$1) -> 16 | G3: =COUNTIFS(Tempat!$I$2:$I$1789,$A3,Tempat!$D$2:$D$1789,G$1) -> 3 | H3: =COUNTIFS(Tempat!$I$2:$I$1789,$A3,Tempat!$D$2:$D$1789,H$1) -> 1 | I3: =COUNTIFS(Tempat!$I$2:$I$1789,$A3,Tempat!$D$2:$D$1789,I$1) -> 4 | J3: =COUNTIFS(Tempat!$I$2:$I$1789,$A3,Tempat!$D$2:$D$1789,J$1) -> 3
A4: Banten | B4: =COUNTIF(Tempat!$I$2:$I$1789,A4) -> 49 | C4: =COUNTIFS(Tempat!$I$2:$I$1789,A4,Tempat!$Q$2:$Q$1789,"Ya") -> 15 | D4: =COUNTIFS(Tempat!$I$2:$I$1789,$A4,Tempat!$D$2:$D$1789,D$1) -> 2 | E4: =COUNTIFS(Tempat!$I$2:$I$1789,$A4,Tempat!$D$2:$D$1789,E$1) -> 22 | F4: =COUNTIFS(Tempat!$I$2:$I$1789,$A4,Tempat!$D$2:$D$1789,F$1) -> 7 | G4: =COUNTIFS(Tempat!$I$2:$I$1789,$A4,Tempat!$D$2:$D$1789,G$1) -> 1 | H4: =COUNTIFS(Tempat!$I$2:$I$1789,$A4,Tempat!$D$2:$D$1789,H$1) -> 0 | I4: =COUNTIFS(Tempat!$I$2:$I$1789,$A4,Tempat!$D$2:$D$1789,I$1) -> 8 | J4: =COUNTIFS(Tempat!$I$2:$I$1789,$A4,Tempat!$D$2:$D$1789,J$1) -> 9
A5: Bengkulu | B5: =COUNTIF(Tempat!$I$2:$I$1789,A5) -> 27 | C5: =COUNTIFS(Tempat!$I$2:$I$1789,A5,Tempat!$Q$2:$Q$1789,"Ya") -> 5 | D5: =COUNTIFS(Tempat!$I$2:$I$1789,$A5,Tempat!$D$2:$D$1789,D$1) -> 0 | E5: =COUNTIFS(Tempat!$I$2:$I$1789,$A5,Tempat!$D$2:$D$1789,E$1) -> 0 | F5: =COUNTIFS(Tempat!$I$2:$I$1789,$A5,Tempat!$D$2:$D$1789,F$1) -> 16 | G5: =COUNTIFS(Tempat!$I$2:$I$1789,$A5,Tempat!$D$2:$D$1789,G$1) -> 1 | H5: =COUNTIFS(Tempat!$I$2:$I$1789,$A5,Tempat!$D$2:$D$1789,H$1) -> 0 | I5: =COUNTIFS(Tempat!$I$2:$I$1789,$A5,Tempat!$D$2:$D$1789,I$1) -> 7 | J5: =COUNTIFS(Tempat!$I$2:$I$1789,$A5,Tempat!$D$2:$D$1789,J$1) -> 3
A6: DI Yogyakarta | B6: =COUNTIF(Tempat!$I$2:$I$1789,A6) -> 104 | C6: =COUNTIFS(Tempat!$I$2:$I$1789,A6,Tempat!$Q$2:$Q$1789,"Ya") -> 36 | D6: =COUNTIFS(Tempat!$I$2:$I$1789,$A6,Tempat!$D$2:$D$1789,D$1) -> 6 | E6: =COUNTIFS(Tempat!$I$2:$I$1789,$A6,Tempat!$D$2:$D$1789,E$1) -> 40 | F6: =COUNTIFS(Tempat!$I$2:$I$1789,$A6,Tempat!$D$2:$D$1789,F$1) -> 19 | G6: =COUNTIFS(Tempat!$I$2:$I$1789,$A6,Tempat!$D$2:$D$1789,G$1) -> 4 | H6: =COUNTIFS(Tempat!$I$2:$I$1789,$A6,Tempat!$D$2:$D$1789,H$1) -> 4 | I6: =COUNTIFS(Tempat!$I$2:$I$1789,$A6,Tempat!$D$2:$D$1789,I$1) -> 14 | J6: =COUNTIFS(Tempat!$I$2:$I$1789,$A6,Tempat!$D$2:$D$1789,J$1) -> 17
A7: DKI Jakarta | B7: =COUNTIF(Tempat!$I$2:$I$1789,A7) -> 264 | C7: =COUNTIFS(Tempat!$I$2:$I$1789,A7,Tempat!$Q$2:$Q$1789,"Ya") -> 66 | D7: =COUNTIFS(Tempat!$I$2:$I$1789,$A7,Tempat!$D$2:$D$1789,D$1) -> 34 | E7: =COUNTIFS(Tempat!$I$2:$I$1789,$A7,Tempat!$D$2:$D$1789,E$1) -> 139 | F7: =COUNTIFS(Tempat!$I$2:$I$1789,$A7,Tempat!$D$2:$D$1789,F$1) -> 10 | G7: =COUNTIFS(Tempat!$I$2:$I$1789,$A7,Tempat!$D$2:$D$1789,G$1) -> 15 | H7: =COUNTIFS(Tempat!$I$2:$I$1789,$A7,Tempat!$D$2:$D$1789,H$1) -> 7 | I7: =COUNTIFS(Tempat!$I$2:$I$1789,$A7,Tempat!$D$2:$D$1789,I$1) -> 21 | J7: =COUNTIFS(Tempat!$I$2:$I$1789,$A7,Tempat!$D$2:$D$1789,J$1) -> 38
A8: Gorontalo | B8: =COUNTIF(Tempat!$I$2:$I$1789,A8) -> 17 | C8: =COUNTIFS(Tempat!$I$2:$I$1789,A8,Tempat!$Q$2:$Q$1789,"Ya") -> 0 | D8: =COUNTIFS(Tempat!$I$2:$I$1789,$A8,Tempat!$D$2:$D$1789,D$1) -> 1 | E8: =COUNTIFS(Tempat!$I$2:$I$1789,$A8,Tempat!$D$2:$D$1789,E$1) -> 3 | F8: =COUNTIFS(Tempat!$I$2:$I$1789,$A8,Tempat!$D$2:$D$1789,F$1) -> 8 | G8: =COUNTIFS(Tempat!$I$2:$I$1789,$A8,Tempat!$D$2:$D$1789,G$1) -> 2 | H8: =COUNTIFS(Tempat!$I$2:$I$1789,$A8,Tempat!$D$2:$D$1789,H$1) -> 0 | I8: =COUNTIFS(Tempat!$I$2:$I$1789,$A8,Tempat!$D$2:$D$1789,I$1) -> 2 | J8: =COUNTIFS(Tempat!$I$2:$I$1789,$A8,Tempat!$D$2:$D$1789,J$1) -> 1
A9: Jambi | B9: =COUNTIF(Tempat!$I$2:$I$1789,A9) -> 24 | C9: =COUNTIFS(Tempat!$I$2:$I$1789,A9,Tempat!$Q$2:$Q$1789,"Ya") -> 0 | D9: =COUNTIFS(Tempat!$I$2:$I$1789,$A9,Tempat!$D$2:$D$1789,D$1) -> 0 | E9: =COUNTIFS(Tempat!$I$2:$I$1789,$A9,Tempat!$D$2:$D$1789,E$1) -> 1 | F9: =COUNTIFS(Tempat!$I$2:$I$1789,$A9,Tempat!$D$2:$D$1789,F$1) -> 10 | G9: =COUNTIFS(Tempat!$I$2:$I$1789,$A9,Tempat!$D$2:$D$1789,G$1) -> 9 | H9: =COUNTIFS(Tempat!$I$2:$I$1789,$A9,Tempat!$D$2:$D$1789,H$1) -> 0 | I9: =COUNTIFS(Tempat!$I$2:$I$1789,$A9,Tempat!$D$2:$D$1789,I$1) -> 3 | J9: =COUNTIFS(Tempat!$I$2:$I$1789,$A9,Tempat!$D$2:$D$1789,J$1) -> 1
A10: Jawa Barat | B10: =COUNTIF(Tempat!$I$2:$I$1789,A10) -> 269 | C10: =COUNTIFS(Tempat!$I$2:$I$1789,A10,Tempat!$Q$2:$Q$1789,"Ya") -> 79 | D10: =COUNTIFS(Tempat!$I$2:$I$1789,$A10,Tempat!$D$2:$D$1789,D$1) -> 44 | E10: =COUNTIFS(Tempat!$I$2:$I$1789,$A10,Tempat!$D$2:$D$1789,E$1) -> 96 | F10: =COUNTIFS(Tempat!$I$2:$I$1789,$A10,Tempat!$D$2:$D$1789,F$1) -> 45 | G10: =COUNTIFS(Tempat!$I$2:$I$1789,$A10,Tempat!$D$2:$D$1789,G$1) -> 11 | H10: =COUNTIFS(Tempat!$I$2:$I$1789,$A10,Tempat!$D$2:$D$1789,H$1) -> 13 | I10: =COUNTIFS(Tempat!$I$2:$I$1789,$A10,Tempat!$D$2:$D$1789,I$1) -> 18 | J10: =COUNTIFS(Tempat!$I$2:$I$1789,$A10,Tempat!$D$2:$D$1789,J$1) -> 42
A11: Jawa Tengah | B11: =COUNTIF(Tempat!$I$2:$I$1789,A11) -> 173 | C11: =COUNTIFS(Tempat!$I$2:$I$1789,A11,Tempat!$Q$2:$Q$1789,"Ya") -> 45 | D11: =COUNTIFS(Tempat!$I$2:$I$1789,$A11,Tempat!$D$2:$D$1789,D$1) -> 30 | E11: =COUNTIFS(Tempat!$I$2:$I$1789,$A11,Tempat!$D$2:$D$1789,E$1) -> 48 | F11: =COUNTIFS(Tempat!$I$2:$I$1789,$A11,Tempat!$D$2:$D$1789,F$1) -> 23 | G11: =COUNTIFS(Tempat!$I$2:$I$1789,$A11,Tempat!$D$2:$D$1789,G$1) -> 19 | H11: =COUNTIFS(Tempat!$I$2:$I$1789,$A11,Tempat!$D$2:$D$1789,H$1) -> 6 | I11: =COUNTIFS(Tempat!$I$2:$I$1789,$A11,Tempat!$D$2:$D$1789,I$1) -> 21 | J11: =COUNTIFS(Tempat!$I$2:$I$1789,$A11,Tempat!$D$2:$D$1789,J$1) -> 26
A12: Jawa Timur | B12: =COUNTIF(Tempat!$I$2:$I$1789,A12) -> 183 | C12: =COUNTIFS(Tempat!$I$2:$I$1789,A12,Tempat!$Q$2:$Q$1789,"Ya") -> 46 | D12: =COUNTIFS(Tempat!$I$2:$I$1789,$A12,Tempat!$D$2:$D$1789,D$1) -> 23 | E12: =COUNTIFS(Tempat!$I$2:$I$1789,$A12,Tempat!$D$2:$D$1789,E$1) -> 69 | F12: =COUNTIFS(Tempat!$I$2:$I$1789,$A12,Tempat!$D$2:$D$1789,F$1) -> 32 | G12: =COUNTIFS(Tempat!$I$2:$I$1789,$A12,Tempat!$D$2:$D$1789,G$1) -> 9 | H12: =COUNTIFS(Tempat!$I$2:$I$1789,$A12,Tempat!$D$2:$D$1789,H$1) -> 11 | I12: =COUNTIFS(Tempat!$I$2:$I$1789,$A12,Tempat!$D$2:$D$1789,I$1) -> 17 | J12: =COUNTIFS(Tempat!$I$2:$I$1789,$A12,Tempat!$D$2:$D$1789,J$1) -> 22
A13: Kalimantan Barat | B13: =COUNTIF(Tempat!$I$2:$I$1789,A13) -> 24 | C13: =COUNTIFS(Tempat!$I$2:$I$1789,A13,Tempat!$Q$2:$Q$1789,"Ya") -> 5 | D13: =COUNTIFS(Tempat!$I$2:$I$1789,$A13,Tempat!$D$2:$D$1789,D$1) -> 4 | E13: =COUNTIFS(Tempat!$I$2:$I$1789,$A13,Tempat!$D$2:$D$1789,E$1) -> 13 | F13: =COUNTIFS(Tempat!$I$2:$I$1789,$A13,Tempat!$D$2:$D$1789,F$1) -> 2 | G13: =COUNTIFS(Tempat!$I$2:$I$1789,$A13,Tempat!$D$2:$D$1789,G$1) -> 0 | H13: =COUNTIFS(Tempat!$I$2:$I$1789,$A13,Tempat!$D$2:$D$1789,H$1) -> 0 | I13: =COUNTIFS(Tempat!$I$2:$I$1789,$A13,Tempat!$D$2:$D$1789,I$1) -> 1 | J13: =COUNTIFS(Tempat!$I$2:$I$1789,$A13,Tempat!$D$2:$D$1789,J$1) -> 4
... A39: Sumatera Utara | B39: =COUNTIF(Tempat!$I$2:$I$1789,A39) -> 53 | C39: =COUNTIFS(Tempat!$I$2:$I$1789,A39,Tempat!$Q$2:$Q$1789,"Ya") -> 18 | D39: =COUNTIFS(Tempat!$I$2:$I$1789,$A39,Tempat!$D$2:$D$1789,D$1) -> 10 | E39: =COUNTIFS(Tempat!$I$2:$I$1789,$A39,Tempat!$D$2:$D$1789,E$1) -> 13 | F39: =COUNTIFS(Tempat!$I$2:$I$1789,$A39,Tempat!$D$2:$D$1789,F$1) -> 15 | G39: =COUNTIFS(Tempat!$I$2:$I$1789,$A39,Tempat!$D$2:$D$1789,G$1) -> 1 | H39: =COUNTIFS(Tempat!$I$2:$I$1789,$A39,Tempat!$D$2:$D$1789,H$1) -> 1 | I39: =COUNTIFS(Tempat!$I$2:$I$1789,$A39,Tempat!$D$2:$D$1789,I$1) -> 9 | J39: =COUNTIFS(Tempat!$I$2:$I$1789,$A39,Tempat!$D$2:$D$1789,J$1) -> 4
A40: Tanpa provinsi (luar negeri / tidak jelas) | B40: =COUNTA(Tempat!A2:A1789)-SUM(B2:B39) -> 44
